[
 {
  "angle": 0.0,
  "dist": 0.0,
  "hidePlane": false,
  "id": 4286773200,
  "index": "PBC007",
  "linkedGunAngles": [],
  "linkedGunName": null,
  "linkedRotationSpeedCoeff": 1.0,
  "model": "content/gameplay/uk/catapult/BC007_Catapult/BC007_Catapult.model",
  "name": "PBC007_Catapult",
  "rotateTime": 0.0,
  "typeinfo": {
   "nation": "United_Kingdom",
   "species": null,
   "type": "Catapult"
  }
 },
 {
  "angle": 0.0,
  "dist": 0.0,
  "hidePlane": false,
  "id": 4285724112,
  "index": "PRC008",
  "linkedGunAngles": [],
  "linkedGunName": null,
  "linkedRotationSpeedCoeff": 1.0,
  "model": "content/gameplay/russia/catapult/RC008_Catapult_K3_21_5m/RC008_Catapult_K3_21_5m.model",
  "name": "PRC008_Catapult_K3_21_5m",
  "rotateTime": 0.0,
  "typeinfo": {
   "nation": "Russia",
   "species": null,
   "type": "Catapult"
  }
 },
 {
  "angle": 0.0,
  "dist": 0.0,
  "hidePlane": false,
  "id": 4282578896,
  "index": "PBC011",
  "linkedGunAngles": [],
  "linkedGunName": null,
  "linkedRotationSpeedCoeff": 1.0,
  "model": "content/gameplay/uk/catapult/BC011_Catapult_46ft_SIIH/BC011_Catapult_46ft_SIIH.model",
  "name": "PBC011_Catapult_46ft_SIIH",
  "rotateTime": 0.0,
  "typeinfo": {
   "nation": "United_Kingdom",
   "species": null,
   "type": "Catapult"
  }
 },
 {
  "angle": 0.0,
  "dist": 0.0,
  "hidePlane": false,
  "id": 4233295856,
  "index": "PAC058",
  "linkedGunAngles": [],
  "linkedGunName": null,
  "linkedRotationSpeedCoeff": 1.0,
  "model": "content/gameplay/usa/catapult/AC058_Catapult_Montana_L_HW19/AC058_Catapult_Montana_L_HW19.model",
  "name": "PAC058_Catapult_Montana_L_HW19",
  "rotateTime": 0.0,
  "typeinfo": {
   "nation": "USA",
   "species": null,
   "type": "Catapult"
  }
 },
 {
  "angle": 0.0,
  "dist": 0.0,
  "hidePlane": false,
  "id": 3246585648,
  "index": "PGC999",
  "linkedGunAngles": [],
  "linkedGunName": null,
  "linkedRotationSpeedCoeff": 1.0,
  "model": "content/gameplay/germany/catapult/GC999_Invisible_catapult/GC999_Invisible_catapult.model",
  "name": "PGC999_Invisible_catapult",
  "rotateTime": 0.0,
  "typeinfo": {
   "nation": "Germany",
   "species": null,
   "type": "Catapult"
  }
 },
 {
  "angle": 0.0,
  "dist": 0.0,
  "hidePlane": false,
  "id": 4283627472,
  "index": "PBC010",
  "linkedGunAngles": [],
  "linkedGunName": null,
  "linkedRotationSpeedCoeff": 1.0,
  "model": "content/gameplay/uk/catapult/BC010_Catapult_46ft_Mk2_R/BC010_Catapult_46ft_Mk2_R.model",
  "name": "PBC010_Catapult_46ft_Mk2_R",
  "rotateTime": 0.0,
  "typeinfo": {
   "nation": "United_Kingdom",
   "species": null,
   "type": "Catapult"
  }
 },
 {
  "angle": 0.0,
  "dist": 0.0,
  "hidePlane": false,
  "id": 4289918800,
  "index": "PFC004",
  "linkedGunAngles": [],
  "linkedGunName": null,
  "linkedRotationSpeedCoeff": 1.0,
  "model": "content/gameplay/france/catapult/FC004_Catapult/FC004_Catapult.model",
  "name": "PFC004_Catapult",
  "rotateTime": 0.0,
  "typeinfo": {
   "nation": "France",
   "species": null,
   "type": "Catapult"
  }
 },
 {
  "angle": 0.0,
  "dist": 0.0,
  "hidePlane": false,
  "id": 4288870192,
  "index": "PGC005",
  "linkedGunAngles": [],
  "linkedGunName": null,
  "linkedRotationSpeedCoeff": 1.0,
  "model": "content/gameplay/germany/catapult/GC005_Catapult_5/GC005_Catapult_5.model",
  "name": "PGC005_Catapult_5",
  "rotateTime": 0.0,
  "typeinfo": {
   "nation": "Germany",
   "species": null,
   "type": "Catapult"
  }
 },
 {
  "angle": 0.0,
  "dist": 0.0,
  "hidePlane": false,
  "id": 4283627248,
  "index": "PIC010",
  "linkedGunAngles": [],
  "linkedGunName": null,
  "linkedRotationSpeedCoeff": 1.0,
  "model": "content/gameplay/italy/catapult/IC010_Catapult/IC010_Catapult.model",
  "name": "PIC010_Catapult",
  "rotateTime": 0.0,
  "typeinfo": {
   "nation": "Italy",
   "species": null,
   "type": "Catapult"
  }
 },
 {
  "angle": 0.0,
  "dist": 0.0,
  "hidePlane": false,
  "id": 4285724656,
  "index": "PAC008",
  "linkedGunAngles": [],
  "linkedGunName": null,
  "linkedRotationSpeedCoeff": 1.0,
  "model": "content/gameplay/usa/catapult/AC008_Catapult_8/AC008_Catapult_8.model",
  "name": "PAC008_Catapult_8",
  "rotateTime": 0.0,
  "typeinfo": {
   "nation": "USA",
   "species": null,
   "type": "Catapult"
  }
 },
 {
  "angle": 0.0,
  "dist": 0.0,
  "hidePlane": false,
  "id": 4290967280,
  "index": "PIC003",
  "linkedGunAngles": [],
  "linkedGunName": null,
  "linkedRotationSpeedCoeff": 1.0,
  "model": "content/gameplay/italy/catapult/IC003_Catapult/IC003_Catapult.model",
  "name": "PIC003_Catapult",
  "rotateTime": 0.0,
  "typeinfo": {
   "nation": "Italy",
   "species": null,
   "type": "Catapult"
  }
 },
 {
  "angle": 0.0,
  "dist": 0.0,
  "hidePlane": false,
  "id": 4286773072,
  "index": "PFC007",
  "linkedGunAngles": [],
  "linkedGunName": null,
  "linkedRotationSpeedCoeff": 1.0,
  "model": "content/gameplay/france/catapult/FC007_Catapult/FC007_Catapult.model",
  "name": "PFC007_Catapult",
  "rotateTime": 0.0,
  "typeinfo": {
   "nation": "France",
   "species": null,
   "type": "Catapult"
  }
 },
 {
  "angle": 0.0,
  "dist": 0.0,
  "hidePlane": false,
  "id": 4292015920,
  "index": "PGC002",
  "linkedGunAngles": [],
  "linkedGunName": null,
  "linkedRotationSpeedCoeff": 1.0,
  "model": "content/gameplay/germany/catapult/GC002_Catapult/GC002_Catapult.model",
  "name": "PGC002_Catapult",
  "rotateTime": 0.0,
  "typeinfo": {
   "nation": "Germany",
   "species": null,
   "type": "Catapult"
  }
 },
 {
  "angle": 0.0,
  "dist": 0.0,
  "hidePlane": false,
  "id": 4287821552,
  "index": "PIC006",
  "linkedGunAngles": [],
  "linkedGunName": null,
  "linkedRotationSpeedCoeff": 1.0,
  "model": "content/gameplay/italy/catapult/IC006_Catapult/IC006_Catapult.model",
  "name": "PIC006_Catapult",
  "rotateTime": 0.0,
  "typeinfo": {
   "nation": "Italy",
   "species": null,
   "type": "Catapult"
  }
 },
 {
  "angle": 0.0,
  "dist": 0.0,
  "hidePlane": false,
  "id": 3765630672,
  "index": "PJC504",
  "linkedGunAngles": [],
  "linkedGunName": null,
  "linkedRotationSpeedCoeff": 1.0,
  "model": "content/gameplay/japan/catapult/JC504_Catapult_Shiki2_Red_Arpeggio/JC504_Catapult_Shiki2_Red_Arpeggio.model",
  "name": "PJC504_Catapult_Shiki2_Red_Arpeggio",
  "rotateTime": 0.0,
  "typeinfo": {
   "nation": "Japan",
   "species": null,
   "type": "Catapult"
  }
 },
 {
  "angle": 0.0,
  "dist": 0.0,
  "hidePlane": false,
  "id": 4279433168,
  "index": "PBC014",
  "linkedGunAngles": [],
  "linkedGunName": null,
  "linkedRotationSpeedCoeff": 1.0,
  "model": "content/gameplay/uk/catapult/BC014_Catapult/BC014_Catapult.model",
  "name": "PBC014_Catapult",
  "rotateTime": 0.0,
  "typeinfo": {
   "nation": "United_Kingdom",
   "species": null,
   "type": "Catapult"
  }
 },
 {
  "angle": 0.0,
  "dist": 0.0,
  "hidePlane": false,
  "id": 3246585840,
  "index": "PAC999",
  "linkedGunAngles": [],
  "linkedGunName": null,
  "linkedRotationSpeedCoeff": 1.0,
  "model": "content/gameplay/usa/catapult/AC999_Invisible_catapult/AC999_Invisible_catapult.model",
  "name": "PAC999_Invisible_catapult",
  "rotateTime": 0.0,
  "typeinfo": {
   "nation": "USA",
   "species": null,
   "type": "Catapult"
  }
 },
 {
  "angle": 0.0,
  "dist": 0.0,
  "hidePlane": false,
  "id": 4292015856,
  "index": "PIC002",
  "linkedGunAngles": [],
  "linkedGunName": null,
  "linkedRotationSpeedCoeff": 1.0,
  "model": "content/gameplay/italy/catapult/IC002_Catapult/IC002_Catapult.model",
  "name": "PIC002_Catapult",
  "rotateTime": 0.0,
  "typeinfo": {
   "nation": "Italy",
   "species": null,
   "type": "Catapult"
  }
 },
 {
  "angle": 0.0,
  "dist": 0.0,
  "hidePlane": false,
  "id": 4293064656,
  "index": "PBC001",
  "linkedGunAngles": [],
  "linkedGunName": null,
  "linkedRotationSpeedCoeff": 1.0,
  "model": "content/gameplay/uk/catapult/BC001_Catapult_1/BC001_Catapult_1.model",
  "name": "PBC001_Catapult_1",
  "rotateTime": 0.0,
  "typeinfo": {
   "nation": "United_Kingdom",
   "species": null,
   "type": "Catapult"
  }
 },
 {
  "angle": 0.0,
  "dist": 0.0,
  "hidePlane": false,
  "id": 4284676048,
  "index": "PBC009",
  "linkedGunAngles": [],
  "linkedGunName": null,
  "linkedRotationSpeedCoeff": 1.0,
  "model": "content/gameplay/uk/catapult/BC009_Catapult_46ft_Mk2/BC009_Catapult_46ft_Mk2.model",
  "name": "PBC009_Catapult_46ft_Mk2",
  "rotateTime": 0.0,
  "typeinfo": {
   "nation": "United_Kingdom",
   "species": null,
   "type": "Catapult"
  }
 },
 {
  "angle": 0.0,
  "dist": 0.0,
  "hidePlane": false,
  "id": 3246585296,
  "index": "PRC999",
  "linkedGunAngles": [],
  "linkedGunName": null,
  "linkedRotationSpeedCoeff": 1.0,
  "model": "content/gameplay/russia/catapult/RC999_Invisible_catapult/RC999_Invisible_catapult.model",
  "name": "PRC999_Invisible_catapult",
  "rotateTime": 0.0,
  "typeinfo": {
   "nation": "Russia",
   "species": null,
   "type": "Catapult"
  }
 },
 {
  "angle": 0.0,
  "dist": 0.0,
  "hidePlane": false,
  "id": 4281530096,
  "index": "PIC012",
  "linkedGunAngles": [],
  "linkedGunName": null,
  "linkedRotationSpeedCoeff": 1.0,
  "model": "content/gameplay/italy/catapult/IC011_Catapult/IC011_Catapult.model",
  "name": "PIC012_Catapult",
  "rotateTime": 0.0,
  "typeinfo": {
   "nation": "Italy",
   "species": null,
   "type": "Catapult"
  }
 },
 {
  "angle": 0.0,
  "dist": 0.0,
  "hidePlane": false,
  "id": 4288870224,
  "index": "PFC005",
  "linkedGunAngles": [],
  "linkedGunName": null,
  "linkedRotationSpeedCoeff": 1.0,
  "model": "content/gameplay/france/catapult/FC005_Catapult_Lorraine/FC005_Catapult_Lorraine.model",
  "name": "PFC005_Catapult_Lorraine",
  "rotateTime": 0.0,
  "typeinfo": {
   "nation": "France",
   "species": null,
   "type": "Catapult"
  }
 },
 {
  "angle": 0.0,
  "dist": 0.0,
  "hidePlane": false,
  "id": 4293064464,
  "index": "PHC001",
  "linkedGunAngles": [],
  "linkedGunName": null,
  "linkedRotationSpeedCoeff": 1.0,
  "model": "content/gameplay/netherlands/catapult/HC001_Heinkel_K8/HC001_Heinkel_K8.model",
  "name": "PHC001_Heinkel_K8",
  "rotateTime": 0.0,
  "typeinfo": {
   "nation": "Netherlands",
   "species": null,
   "type": "Catapult"
  }
 },
 {
  "angle": 0.0,
  "dist": 0.0,
  "hidePlane": false,
  "id": 4289918704,
  "index": "PIC004",
  "linkedGunAngles": [],
  "linkedGunName": null,
  "linkedRotationSpeedCoeff": 1.0,
  "model": "content/gameplay/italy/catapult/IC004_Catapult/IC004_Catapult.model",
  "name": "PIC004_Catapult",
  "rotateTime": 0.0,
  "typeinfo": {
   "nation": "Italy",
   "species": null,
   "type": "Catapult"
  }
 },
 {
  "angle": 0.0,
  "dist": 0.0,
  "hidePlane": false,
  "id": 4292015376,
  "index": "PXC002",
  "linkedGunAngles": [],
  "linkedGunName": null,
  "linkedRotationSpeedCoeff": 1.0,
  "model": "content/gameplay/events/catapult/XC002_Mummy_Catapult/XC002_Mummy_Catapult.model",
  "name": "PXC002_Mummy_Catapult",
  "rotateTime": 0.0,
  "typeinfo": {
   "nation": "Events",
   "species": null,
   "type": "Catapult"
  }
 },
 {
  "angle": 0.0,
  "dist": 0.0,
  "hidePlane": false,
  "id": 4293064432,
  "index": "PIC001",
  "linkedGunAngles": [],
  "linkedGunName": null,
  "linkedRotationSpeedCoeff": 1.0,
  "model": "content/gameplay/italy/catapult/IC001_Catapult/IC001_Catapult.model",
  "name": "PIC001_Catapult",
  "rotateTime": 0.0,
  "typeinfo": {
   "nation": "Italy",
   "species": null,
   "type": "Catapult"
  }
 },
 {
  "angle": 0.0,
  "dist": 0.0,
  "hidePlane": false,
  "id": 4290967504,
  "index": "PBC003",
  "linkedGunAngles": [],
  "linkedGunName": null,
  "linkedRotationSpeedCoeff": 1.0,
  "model": "content/gameplay/uk/catapult/BC003_EIIH_MK_II_53ft/BC003_EIIH_MK_II_53ft.model",
  "name": "PBC003_EIIH_MK_II_53ft",
  "rotateTime": 0.0,
  "typeinfo": {
   "nation": "United_Kingdom",
   "species": null,
   "type": "Catapult"
  }
 },
 {
  "angle": 0.0,
  "dist": 0.0,
  "hidePlane": false,
  "id": 4289918416,
  "index": "PRC004",
  "linkedGunAngles": [],
  "linkedGunName": null,
  "linkedRotationSpeedCoeff": 1.0,
  "model": "content/gameplay/russia/catapult/RC004_Catapult_Y/RC004_Catapult_Y.model",
  "name": "PRC004_Catapult_Y",
  "rotateTime": 0.0,
  "typeinfo": {
   "nation": "Russia",
   "species": null,
   "type": "Catapult"
  }
 },
 {
  "angle": 0.0,
  "dist": 0.0,
  "hidePlane": false,
  "id": 4285724624,
  "index": "PBC008",
  "linkedGunAngles": [],
  "linkedGunName": null,
  "linkedRotationSpeedCoeff": 1.0,
  "model": "content/gameplay/uk/catapult/BC008_Catapult_KingGeorgeV/BC008_Catapult_KingGeorgeV.model",
  "name": "PBC008_Catapult_KingGeorgeV",
  "rotateTime": 0.0,
  "typeinfo": {
   "nation": "United_Kingdom",
   "species": null,
   "type": "Catapult"
  }
 },
 {
  "angle": 0.0,
  "dist": 0.0,
  "hidePlane": false,
  "id": 4286772688,
  "index": "PRC007",
  "linkedGunAngles": [],
  "linkedGunName": null,
  "linkedRotationSpeedCoeff": 1.0,
  "model": "content/gameplay/russia/catapult/RC007_Catapult_K12_Heinshel_2f/RC007_Catapult_K12_Heinshel_2f.model",
  "name": "PRC007_Catapult_K12_Heinshel_2f",
  "rotateTime": 0.0,
  "typeinfo": {
   "nation": "Russia",
   "species": null,
   "type": "Catapult"
  }
 },
 {
  "angle": 0.0,
  "dist": 0.0,
  "hidePlane": false,
  "id": 4289918672,
  "index": "PJC004",
  "linkedGunAngles": [],
  "linkedGunName": null,
  "linkedRotationSpeedCoeff": 1.0,
  "model": "content/gameplay/japan/catapult/JC004_Catapult_Type2_N1_model12/JC004_Catapult_Type2_N1_model12.model",
  "name": "PJC004_Catapult_Type2_N1_model12",
  "rotateTime": 0.0,
  "typeinfo": {
   "nation": "Japan",
   "species": null,
   "type": "Catapult"
  }
 },
 {
  "angle": 0.0,
  "dist": 0.0,
  "hidePlane": false,
  "id": 4290967536,
  "index": "PAC003",
  "linkedGunAngles": [],
  "linkedGunName": null,
  "linkedRotationSpeedCoeff": 1.0,
  "model": "content/gameplay/usa/catapult/AC003_Catapult_3/AC003_Catapult_3.model",
  "name": "PAC003_Catapult_3",
  "rotateTime": 0.0,
  "typeinfo": {
   "nation": "USA",
   "species": null,
   "type": "Catapult"
  }
 },
 {
  "angle": 0.0,
  "dist": 0.0,
  "hidePlane": false,
  "id": 4289918960,
  "index": "PAC004",
  "linkedGunAngles": [],
  "linkedGunName": null,
  "linkedRotationSpeedCoeff": 1.0,
  "model": "content/gameplay/usa/catapult/AC004_Catapult_4/AC004_Catapult_4.model",
  "name": "PAC004_Catapult_4",
  "rotateTime": 0.0,
  "typeinfo": {
   "nation": "USA",
   "species": null,
   "type": "Catapult"
  }
 },
 {
  "angle": 0.0,
  "dist": 0.0,
  "hidePlane": false,
  "id": 4279433008,
  "index": "PGC014",
  "linkedGunAngles": [],
  "linkedGunName": null,
  "linkedRotationSpeedCoeff": 1.0,
  "model": "content/gameplay/germany/catapult/GC014_Catapult_Weser/GC014_Catapult_Weser.model",
  "name": "PGC014_Catapult_Weser",
  "rotateTime": 0.0,
  "typeinfo": {
   "nation": "Germany",
   "species": null,
   "type": "Catapult"
  }
 },
 {
  "angle": 0.0,
  "dist": 0.0,
  "hidePlane": false,
  "id": 4290966736,
  "index": "PZC003",
  "linkedGunAngles": [],
  "linkedGunName": null,
  "linkedRotationSpeedCoeff": 1.0,
  "model": "content/gameplay/panasia/catapult/ZC003_Catapult/ZC003_Catapult.model",
  "name": "PZC003_Catapult",
  "rotateTime": 0.0,
  "typeinfo": {
   "nation": "Pan_Asia",
   "species": null,
   "type": "Catapult"
  }
 },
 {
  "angle": 0.0,
  "dist": 0.0,
  "hidePlane": false,
  "id": 4286772976,
  "index": "PIC007",
  "linkedGunAngles": [],
  "linkedGunName": null,
  "linkedRotationSpeedCoeff": 1.0,
  "model": "content/gameplay/italy/catapult/IC007_Catapult_Giussano/IC007_Catapult_Giussano.model",
  "name": "PIC007_Catapult_Giussano",
  "rotateTime": 0.0,
  "typeinfo": {
   "nation": "Italy",
   "species": null,
   "type": "Catapult"
  }
 },
 {
  "angle": 0.0,
  "dist": 0.0,
  "hidePlane": false,
  "id": 4231198704,
  "index": "PAC060",
  "linkedGunAngles": [],
  "linkedGunName": null,
  "linkedRotationSpeedCoeff": 1.0,
  "model": "content/gameplay/usa/catapult/AC060_Catapult_Montana_R_HW19/AC060_Catapult_Montana_R_HW19.model",
  "name": "PAC060_Catapult_Montana_R_HW19",
  "rotateTime": 0.0,
  "typeinfo": {
   "nation": "USA",
   "species": null,
   "type": "Catapult"
  }
 },
 {
  "angle": 0.0,
  "dist": 0.0,
  "hidePlane": false,
  "id": 4285724400,
  "index": "PIC008",
  "linkedGunAngles": [],
  "linkedGunName": null,
  "linkedRotationSpeedCoeff": 1.0,
  "model": "content/gameplay/italy/catapult/IC008_Catapult/IC008_Catapult.model",
  "name": "PIC008_Catapult",
  "rotateTime": 0.0,
  "typeinfo": {
   "nation": "Italy",
   "species": null,
   "type": "Catapult"
  }
 },
 {
  "angle": 0.0,
  "dist": 0.0,
  "hidePlane": false,
  "id": 4293064144,
  "index": "PRC001",
  "linkedGunAngles": [],
  "linkedGunName": null,
  "linkedRotationSpeedCoeff": 1.0,
  "model": "content/gameplay/russia/catapult/RC001_Catapult_1/RC001_Catapult_1.model",
  "name": "PRC001_Catapult_1",
  "rotateTime": 0.0,
  "typeinfo": {
   "nation": "Russia",
   "species": null,
   "type": "Catapult"
  }
 },
 {
  "angle": 0.0,
  "dist": 0.0,
  "hidePlane": false,
  "id": 4292015952,
  "index": "PFC002",
  "linkedGunAngles": [],
  "linkedGunName": null,
  "linkedRotationSpeedCoeff": 1.0,
  "model": "content/gameplay/france/catapult/FC002_Catapult/FC002_Catapult.model",
  "name": "PFC002_Catapult",
  "rotateTime": 0.0,
  "typeinfo": {
   "nation": "France",
   "species": null,
   "type": "Catapult"
  }
 },
 {
  "angle": 0.0,
  "dist": 0.0,
  "hidePlane": false,
  "id": 4288870128,
  "index": "PIC005",
  "linkedGunAngles": [],
  "linkedGunName": null,
  "linkedRotationSpeedCoeff": 1.0,
  "model": "content/gameplay/italy/catapult/IC005_Catapult/IC005_Catapult.model",
  "name": "PIC005_Catapult",
  "rotateTime": 0.0,
  "typeinfo": {
   "nation": "Italy",
   "species": null,
   "type": "Catapult"
  }
 },
 {
  "angle": 0.0,
  "dist": 0.0,
  "hidePlane": false,
  "id": 3246585808,
  "index": "PBC999",
  "linkedGunAngles": [],
  "linkedGunName": null,
  "linkedRotationSpeedCoeff": 1.0,
  "model": "content/gameplay/uk/catapult/BC999_Invisible_catapult/BC999_Invisible_catapult.model",
  "name": "PBC999_Invisible_catapult",
  "rotateTime": 0.0,
  "typeinfo": {
   "nation": "United_Kingdom",
   "species": null,
   "type": "Catapult"
  }
 },
 {
  "angle": 0.0,
  "dist": 0.0,
  "hidePlane": false,
  "id": 4287821648,
  "index": "PFC006",
  "linkedGunAngles": [],
  "linkedGunName": null,
  "linkedRotationSpeedCoeff": 1.0,
  "model": "content/gameplay/france/catapult/FC006_Catatpult/FC006_Catatpult.model",
  "name": "PFC006_Catatpult",
  "rotateTime": 0.0,
  "typeinfo": {
   "nation": "France",
   "species": null,
   "type": "Catapult"
  }
 },
 {
  "angle": 0.0,
  "dist": 0.0,
  "hidePlane": false,
  "id": 4287821776,
  "index": "PBC006",
  "linkedGunAngles": [],
  "linkedGunName": null,
  "linkedRotationSpeedCoeff": 1.0,
  "model": "content/gameplay/uk/catapult/BC006_Catapult/BC006_Catapult.model",
  "name": "PBC006_Catapult",
  "rotateTime": 0.0,
  "typeinfo": {
   "nation": "United_Kingdom",
   "species": null,
   "type": "Catapult"
  }
 },
 {
  "angle": 0.0,
  "dist": 0.0,
  "hidePlane": false,
  "id": 4232247280,
  "index": "PAC059",
  "linkedGunAngles": [],
  "linkedGunName": null,
  "linkedRotationSpeedCoeff": 1.0,
  "model": "content/gameplay/usa/catapult/AC059_Catapult_Alaska_HW19/AC059_Catapult_Alaska_HW19.model",
  "name": "PAC059_Catapult_Alaska_HW19",
  "rotateTime": 0.0,
  "typeinfo": {
   "nation": "USA",
   "species": null,
   "type": "Catapult"
  }
 },
 {
  "angle": 0.0,
  "dist": 0.0,
  "hidePlane": false,
  "id": 4287821520,
  "index": "PJC006",
  "linkedGunAngles": [],
  "linkedGunName": null,
  "linkedRotationSpeedCoeff": 1.0,
  "model": "content/gameplay/japan/catapult/JC006_Catapult/JC006_Catapult.model",
  "name": "PJC006_Catapult",
  "rotateTime": 0.0,
  "typeinfo": {
   "nation": "Japan",
   "species": null,
   "type": "Catapult"
  }
 },
 {
  "angle": 0.0,
  "dist": 0.0,
  "hidePlane": false,
  "id": 4292015312,
  "index": "PZC002",
  "linkedGunAngles": [],
  "linkedGunName": null,
  "linkedRotationSpeedCoeff": 1.0,
  "model": "content/gameplay/panasia/catapult/ZC002_Catapult/ZC002_Catapult.model",
  "name": "PZC002_Catapult",
  "rotateTime": 0.0,
  "typeinfo": {
   "nation": "Pan_Asia",
   "species": null,
   "type": "Catapult"
  }
 },
 {
  "angle": 0.0,
  "dist": 0.0,
  "hidePlane": false,
  "id": 4280481744,
  "index": "PBC013",
  "linkedGunAngles": [],
  "linkedGunName": null,
  "linkedRotationSpeedCoeff": 1.0,
  "model": "content/gameplay/uk/catapult/BC013_Catapult/BC013_Catapult.model",
  "name": "PBC013_Catapult",
  "rotateTime": 0.0,
  "typeinfo": {
   "nation": "United_Kingdom",
   "species": null,
   "type": "Catapult"
  }
 },
 {
  "angle": 0.0,
  "dist": 0.0,
  "hidePlane": false,
  "id": 3768776528,
  "index": "PFC501",
  "linkedGunAngles": [],
  "linkedGunName": null,
  "linkedRotationSpeedCoeff": 1.0,
  "model": "content/gameplay/france/catapult/FC501_Catatpult_Nolan/FC501_Catatpult_Nolan.model",
  "name": "PFC501_Catatpult_Nolan",
  "rotateTime": 0.0,
  "typeinfo": {
   "nation": "France",
   "species": null,
   "type": "Catapult"
  }
 },
 {
  "angle": 0.0,
  "dist": 0.0,
  "hidePlane": false,
  "id": 4280481584,
  "index": "PGC013",
  "linkedGunAngles": [],
  "linkedGunName": null,
  "linkedRotationSpeedCoeff": 1.0,
  "model": "content/gameplay/germany/catapult/GC013_Catapult_Odin/GC013_Catapult_Odin.model",
  "name": "PGC013_Catapult_Odin",
  "rotateTime": 0.0,
  "typeinfo": {
   "nation": "Germany",
   "species": null,
   "type": "Catapult"
  }
 },
 {
  "angle": 0.0,
  "dist": 0.0,
  "hidePlane": false,
  "id": 4288870352,
  "index": "PBC005",
  "linkedGunAngles": [],
  "linkedGunName": null,
  "linkedRotationSpeedCoeff": 1.0,
  "model": "content/gameplay/uk/catapult/BC005_DIIIH_MK_III_91ft/BC005_DIIIH_MK_III_91ft.model",
  "name": "PBC005_DIIIH_MK_III_91ft",
  "rotateTime": 0.0,
  "typeinfo": {
   "nation": "United_Kingdom",
   "species": null,
   "type": "Catapult"
  }
 },
 {
  "angle": 0.0,
  "dist": 0.0,
  "hidePlane": false,
  "id": 4290966992,
  "index": "PRC003",
  "linkedGunAngles": [],
  "linkedGunName": null,
  "linkedRotationSpeedCoeff": 1.0,
  "model": "content/gameplay/russia/catapult/RC003_Catapult_K12_Heinshel/RC003_Catapult_K12_Heinshel.model",
  "name": "PRC003_Catapult_K12_Heinshel",
  "rotateTime": 0.0,
  "typeinfo": {
   "nation": "Russia",
   "species": null,
   "type": "Catapult"
  }
 },
 {
  "angle": 0.0,
  "dist": 0.0,
  "hidePlane": false,
  "id": 4285724464,
  "index": "PGC008",
  "linkedGunAngles": [],
  "linkedGunName": null,
  "linkedRotationSpeedCoeff": 1.0,
  "model": "content/gameplay/germany/catapult/GC008_Catapult_8/GC008_Catapult_8.model",
  "name": "PGC008_Catapult_8",
  "rotateTime": 0.0,
  "typeinfo": {
   "nation": "Germany",
   "species": null,
   "type": "Catapult"
  }
 },
 {
  "angle": 0.0,
  "dist": 0.0,
  "hidePlane": false,
  "id": 4284675824,
  "index": "PIC009",
  "linkedGunAngles": [],
  "linkedGunName": null,
  "linkedRotationSpeedCoeff": 1.0,
  "model": "content/gameplay/italy/catapult/IC009_Catapult/IC009_Catapult.model",
  "name": "PIC009_Catapult",
  "rotateTime": 0.0,
  "typeinfo": {
   "nation": "Italy",
   "species": null,
   "type": "Catapult"
  }
 },
 {
  "angle": 0.0,
  "dist": 0.0,
  "hidePlane": false,
  "id": 4228052976,
  "index": "PAC063",
  "linkedGunAngles": [],
  "linkedGunName": null,
  "linkedRotationSpeedCoeff": 1.0,
  "model": "content/gameplay/usa/catapult/AC063_Catapult_2_LOGH/AC063_Catapult_2_LOGH.model",
  "name": "PAC063_Catapult_2_LOGH",
  "rotateTime": 0.0,
  "typeinfo": {
   "nation": "USA",
   "species": null,
   "type": "Catapult"
  }
 },
 {
  "angle": 0.0,
  "dist": 0.0,
  "hidePlane": false,
  "id": 4293064496,
  "index": "PGC001",
  "linkedGunAngles": [],
  "linkedGunName": null,
  "linkedRotationSpeedCoeff": 1.0,
  "model": "content/gameplay/germany/catapult/GC001_Catapult_1/GC001_Catapult_1.model",
  "name": "PGC001_Catapult_1",
  "rotateTime": 0.0,
  "typeinfo": {
   "nation": "Germany",
   "species": null,
   "type": "Catapult"
  }
 },
 {
  "angle": 0.0,
  "dist": 0.0,
  "hidePlane": false,
  "id": 4287821264,
  "index": "PRC006",
  "linkedGunAngles": [],
  "linkedGunName": null,
  "linkedRotationSpeedCoeff": 1.0,
  "model": "content/gameplay/russia/catapult/RC006_Catapult_HK20/RC006_Catapult_HK20.model",
  "name": "PRC006_Catapult_HK20",
  "rotateTime": 0.0,
  "typeinfo": {
   "nation": "Russia",
   "species": null,
   "type": "Catapult"
  }
 },
 {
  "angle": 0.0,
  "dist": 0.0,
  "hidePlane": false,
  "id": 4293064528,
  "index": "PFC001",
  "linkedGunAngles": [],
  "linkedGunName": null,
  "linkedRotationSpeedCoeff": 1.0,
  "model": "content/gameplay/france/catapult/FC001_Catatpult/FC001_Catatpult.model",
  "name": "PFC001_Catatpult",
  "rotateTime": 0.0,
  "typeinfo": {
   "nation": "France",
   "species": null,
   "type": "Catapult"
  }
 },
 {
  "angle": 0.0,
  "dist": 0.0,
  "hidePlane": false,
  "id": 4292015824,
  "index": "PJC002",
  "linkedGunAngles": [],
  "linkedGunName": null,
  "linkedRotationSpeedCoeff": 1.0,
  "model": "content/gameplay/japan/catapult/JC002_Catapult/JC002_Catapult.model",
  "name": "PJC002_Catapult",
  "rotateTime": 0.0,
  "typeinfo": {
   "nation": "Japan",
   "species": null,
   "type": "Catapult"
  }
 },
 {
  "angle": 0.0,
  "dist": 0.0,
  "hidePlane": false,
  "id": 4292015568,
  "index": "PRC002",
  "linkedGunAngles": [],
  "linkedGunName": null,
  "linkedRotationSpeedCoeff": 1.0,
  "model": "content/gameplay/russia/catapult/RC002_Catapult_3K_2b/RC002_Catapult_3K_2b.model",
  "name": "PRC002_Catapult_3K_2b",
  "rotateTime": 0.0,
  "typeinfo": {
   "nation": "Russia",
   "species": null,
   "type": "Catapult"
  }
 },
 {
  "angle": 0.0,
  "dist": 0.0,
  "hidePlane": false,
  "id": 3766679248,
  "index": "PJC503",
  "linkedGunAngles": [],
  "linkedGunName": null,
  "linkedRotationSpeedCoeff": 1.0,
  "model": "content/gameplay/japan/catapult/JC503_Catapult_Type2_N1_model12_HW19/JC503_Catapult_Type2_N1_model12_HW19.model",
  "name": "PJC503_Catapult_Type2_N1_model12_HW19",
  "rotateTime": 0.0,
  "typeinfo": {
   "nation": "Japan",
   "species": null,
   "type": "Catapult"
  }
 },
 {
  "angle": 0.0,
  "dist": 0.0,
  "hidePlane": false,
  "id": 4293064400,
  "index": "PJC001",
  "linkedGunAngles": [],
  "linkedGunName": null,
  "linkedRotationSpeedCoeff": 1.0,
  "model": "content/gameplay/japan/catapult/JC001_Catapult_Shiki2/JC001_Catapult_Shiki2.model",
  "name": "PJC001_Catapult_Shiki2",
  "rotateTime": 0.0,
  "typeinfo": {
   "nation": "Japan",
   "species": null,
   "type": "Catapult"
  }
 },
 {
  "angle": 0.0,
  "dist": 0.0,
  "hidePlane": false,
  "id": 4290967344,
  "index": "PGC003",
  "linkedGunAngles": [],
  "linkedGunName": null,
  "linkedRotationSpeedCoeff": 1.0,
  "model": "content/gameplay/germany/catapult/GC003_Catapult/GC003_Catapult.model",
  "name": "PGC003_Catapult",
  "rotateTime": 0.0,
  "typeinfo": {
   "nation": "Germany",
   "species": null,
   "type": "Catapult"
  }
 },
 {
  "angle": 0.0,
  "dist": 0.0,
  "hidePlane": false,
  "id": 4284675888,
  "index": "PGC009",
  "linkedGunAngles": [],
  "linkedGunName": null,
  "linkedRotationSpeedCoeff": 1.0,
  "model": "content/gameplay/germany/catapult/GC009_Catapult_4_Ice/GC009_Catapult_4_Ice.model",
  "name": "PGC009_Catapult_4_Ice",
  "rotateTime": 0.0,
  "typeinfo": {
   "nation": "Germany",
   "species": null,
   "type": "Catapult"
  }
 },
 {
  "angle": 0.0,
  "dist": 0.0,
  "hidePlane": false,
  "id": 4278384592,
  "index": "PBC015",
  "linkedGunAngles": [],
  "linkedGunName": null,
  "linkedRotationSpeedCoeff": 1.0,
  "model": "content/gameplay/uk/catapult/BC015_Catapult_D_II_H/BC015_Catapult_D_II_H.model",
  "name": "PBC015_Catapult_D_II_H",
  "rotateTime": 0.0,
  "typeinfo": {
   "nation": "United_Kingdom",
   "species": null,
   "type": "Catapult"
  }
 },
 {
  "angle": 0.0,
  "dist": 0.0,
  "hidePlane": false,
  "id": 4290967376,
  "index": "PFC003",
  "linkedGunAngles": [],
  "linkedGunName": null,
  "linkedRotationSpeedCoeff": 1.0,
  "model": "content/gameplay/france/catapult/FC003_Catapult/FC003_Catapult.model",
  "name": "PFC003_Catapult",
  "rotateTime": 0.0,
  "typeinfo": {
   "nation": "France",
   "species": null,
   "type": "Catapult"
  }
 },
 {
  "angle": 0.0,
  "dist": 0.0,
  "hidePlane": false,
  "id": 4286773040,
  "index": "PGC007",
  "linkedGunAngles": [],
  "linkedGunName": null,
  "linkedRotationSpeedCoeff": 1.0,
  "model": "content/gameplay/germany/catapult/GC007_Catapult_7/GC007_Catapult_7.model",
  "name": "PGC007_Catapult_7",
  "rotateTime": 0.0,
  "typeinfo": {
   "nation": "Germany",
   "species": null,
   "type": "Catapult"
  }
 },
 {
  "angle": 0.0,
  "dist": 0.0,
  "hidePlane": false,
  "id": 4290967312,
  "index": "PHC003",
  "linkedGunAngles": [],
  "linkedGunName": null,
  "linkedRotationSpeedCoeff": 1.0,
  "model": "content/gameplay/netherlands/catapult/HC003_Catapult/HC003_Catapult.model",
  "name": "PHC003_Catapult",
  "rotateTime": 0.0,
  "typeinfo": {
   "nation": "Netherlands",
   "species": null,
   "type": "Catapult"
  }
 },
 {
  "angle": 0.0,
  "dist": 0.0,
  "hidePlane": false,
  "id": 4289918768,
  "index": "PGC004",
  "linkedGunAngles": [],
  "linkedGunName": null,
  "linkedRotationSpeedCoeff": 1.0,
  "model": "content/gameplay/germany/catapult/GC004_Catapult_4/GC004_Catapult_4.model",
  "name": "PGC004_Catapult_4",
  "rotateTime": 0.0,
  "typeinfo": {
   "nation": "Germany",
   "species": null,
   "type": "Catapult"
  }
 },
 {
  "angle": 0.0,
  "dist": 0.0,
  "hidePlane": false,
  "id": 4282578672,
  "index": "PIC011",
  "linkedGunAngles": [],
  "linkedGunName": null,
  "linkedRotationSpeedCoeff": 1.0,
  "model": "content/gameplay/italy/catapult/IC011_Catapult_B/IC011_Catapult_B.model",
  "name": "PIC011_Catapult_B",
  "rotateTime": 0.0,
  "typeinfo": {
   "nation": "Italy",
   "species": null,
   "type": "Catapult"
  }
 },
 {
  "angle": 0.0,
  "dist": 0.0,
  "hidePlane": false,
  "id": 4287821616,
  "index": "PGC006",
  "linkedGunAngles": [],
  "linkedGunName": null,
  "linkedRotationSpeedCoeff": 1.0,
  "model": "content/gameplay/germany/catapult/GC006_Catapult_6/GC006_Catapult_6.model",
  "name": "PGC006_Catapult_6",
  "rotateTime": 0.0,
  "typeinfo": {
   "nation": "Germany",
   "species": null,
   "type": "Catapult"
  }
 },
 {
  "angle": 0.0,
  "dist": 0.0,
  "hidePlane": false,
  "id": 3768776496,
  "index": "PGC501",
  "linkedGunAngles": [],
  "linkedGunName": null,
  "linkedRotationSpeedCoeff": 1.0,
  "model": "content/gameplay/germany/catapult/GC501_Catapult_space/GC501_Catapult_space.model",
  "name": "PGC501_Catapult_space",
  "rotateTime": 0.0,
  "typeinfo": {
   "nation": "Germany",
   "species": null,
   "type": "Catapult"
  }
 },
 {
  "angle": 0.0,
  "dist": 0.0,
  "hidePlane": false,
  "id": 4292016080,
  "index": "PBC002",
  "linkedGunAngles": [],
  "linkedGunName": null,
  "linkedRotationSpeedCoeff": 1.0,
  "model": "content/gameplay/uk/catapult/BC002_DIH_MK_I_91ft/BC002_DIH_MK_I_91ft.model",
  "name": "PBC002_DIH_MK_I_91ft",
  "rotateTime": 0.0,
  "typeinfo": {
   "nation": "United_Kingdom",
   "species": null,
   "type": "Catapult"
  }
 },
 {
  "angle": 0.0,
  "dist": 0.0,
  "hidePlane": false,
  "id": 4281530160,
  "index": "PGC012",
  "linkedGunAngles": [],
  "linkedGunName": null,
  "linkedRotationSpeedCoeff": 1.0,
  "model": "content/gameplay/germany/catapult/GC012_Catapult_9/GC012_Catapult_9.model",
  "name": "PGC012_Catapult_9",
  "rotateTime": 0.0,
  "typeinfo": {
   "nation": "Germany",
   "species": null,
   "type": "Catapult"
  }
 },
 {
  "angle": 0.0,
  "dist": 0.0,
  "hidePlane": false,
  "id": 4292016112,
  "index": "PAC002",
  "linkedGunAngles": [],
  "linkedGunName": null,
  "linkedRotationSpeedCoeff": 1.0,
  "model": "content/gameplay/usa/catapult/AC002_Catapult_2/AC002_Catapult_2.model",
  "name": "PAC002_Catapult_2",
  "rotateTime": 0.0,
  "typeinfo": {
   "nation": "USA",
   "species": null,
   "type": "Catapult"
  }
 },
 {
  "angle": 0.0,
  "dist": 0.0,
  "hidePlane": false,
  "id": 4288870096,
  "index": "PJC005",
  "linkedGunAngles": [],
  "linkedGunName": null,
  "linkedRotationSpeedCoeff": 1.0,
  "model": "content/gameplay/japan/catapult/JC005_Catapult_Space/JC005_Catapult_Space.model",
  "name": "PJC005_Catapult_Space",
  "rotateTime": 0.0,
  "typeinfo": {
   "nation": "Japan",
   "species": null,
   "type": "Catapult"
  }
 },
 {
  "angle": 0.0,
  "dist": 0.0,
  "hidePlane": false,
  "id": 4293063888,
  "index": "PZC001",
  "linkedGunAngles": [],
  "linkedGunName": null,
  "linkedRotationSpeedCoeff": 1.0,
  "model": "content/gameplay/panasia/catapult/ZC001_Catapult/ZC001_Catapult.model",
  "name": "PZC001_Catapult",
  "rotateTime": 0.0,
  "typeinfo": {
   "nation": "Pan_Asia",
   "species": null,
   "type": "Catapult"
  }
 },
 {
  "angle": 0.0,
  "dist": 0.0,
  "hidePlane": false,
  "id": 4293064688,
  "index": "PAC001",
  "linkedGunAngles": [],
  "linkedGunName": null,
  "linkedRotationSpeedCoeff": 1.0,
  "model": "content/gameplay/usa/catapult/AC001_Catapult_1/AC001_Catapult_1.model",
  "name": "PAC001_Catapult_1",
  "rotateTime": 0.0,
  "typeinfo": {
   "nation": "USA",
   "species": null,
   "type": "Catapult"
  }
 },
 {
  "angle": 0.0,
  "dist": 0.0,
  "hidePlane": false,
  "id": 4283627504,
  "index": "PAC010",
  "linkedGunAngles": [],
  "linkedGunName": null,
  "linkedRotationSpeedCoeff": 1.0,
  "model": "content/gameplay/usa/catapult/AC010_Catapult/AC010_Catapult.model",
  "name": "PAC010_Catapult",
  "rotateTime": 0.0,
  "typeinfo": {
   "nation": "USA",
   "species": null,
   "type": "Catapult"
  }
 },
 {
  "angle": 0.0,
  "dist": 0.0,
  "hidePlane": false,
  "id": 4281530320,
  "index": "PBC012",
  "linkedGunAngles": [],
  "linkedGunName": null,
  "linkedRotationSpeedCoeff": 1.0,
  "model": "content/gameplay/uk/catapult/BC012_DIH_MK_I_91ft/BC012_DIH_MK_I_91ft.model",
  "name": "PBC012_DIH_MK_I_91ft",
  "rotateTime": 0.0,
  "typeinfo": {
   "nation": "United_Kingdom",
   "species": null,
   "type": "Catapult"
  }
 }
]