[
 {
  "caption": "PCOI002",
  "enabled": true,
  "failureEvents": [],
  "failureEventsCheckType": {},
  "id": 4292593584,
  "index": "PCOI002",
  "name": "PCOI002_RibbonsFire2",
  "restrictions": {
   "forbiddenShips": [
    "PASA110_Midway",
    "PBSB105_Iron_Duke",
    "PBSB107_King_George_V",
    "PBSB517_Nelson",
    "PBSB527_Duke_of_York",
    "PBSB108_Monarch",
    "PBSB109_Lion",
    "PBSB110_Conqueror"
   ],
   "subtype": [
    "Battleship",
    "AirCarrier",
    "Destroyer"
   ]
  },
  "successEvents": [
   {
    "count": 2,
    "gainer": "owner",
    "name": "RibbonGained",
    "ribbonType": [
     "BURN"
    ]
   }
  ],
  "successEventsCheckType": {},
  "successOnBattleEnd": false,
  "typeinfo": {
   "nation": "Common",
   "species": "IndividualTask",
   "type": "Other"
  }
 },
 {
  "caption": "PCOI023",
  "enabled": true,
  "failureEvents": [],
  "failureEventsCheckType": {},
  "id": 4270573488,
  "index": "PCOI023",
  "name": "PCOI023_RibbonsPlane6",
  "restrictions": {
   "level": [
    8
   ],
   "subtype": "AirCarrier"
  },
  "successEvents": [
   {
    "count": 6,
    "gainer": "owner",
    "name": "RibbonGained",
    "ribbonType": [
     "PLANE",
     "SPLANE"
    ]
   }
  ],
  "successEventsCheckType": {},
  "successOnBattleEnd": false,
  "typeinfo": {
   "nation": "Common",
   "species": "IndividualTask",
   "type": "Other"
  }
 },
 {
  "caption": "PCOI006",
  "enabled": true,
  "failureEvents": [],
  "failureEventsCheckType": {},
  "id": 4288399280,
  "index": "PCOI006",
  "name": "PCOI006_Ribbons90",
  "restrictions": {
   "specificShips": [
    "PBSC110_Minotaur",
    "PJSD108_Akizuki",
    "PJSD219_Kitakaze",
    "PJSD210_Harugumo",
    "PASC210_Worcester",
    "PRSD110_Pr_24_Khabarovsk",
    "PBSD110_Daring"
   ]
  },
  "successEvents": [
   {
    "count": 90,
    "gainer": "owner",
    "name": "RibbonGained",
    "ribbonType": [
     "MAIN_CALIBER_OVER_PENETRATION",
     "MAIN_CALIBER_PENETRATION",
     "MAIN_CALIBER_NO_PENETRATION",
     "MAIN_CALIBER_RICOCHET",
     "TORPEDO",
     "BOMB",
     "PLANE",
     "CRIT",
     "FRAG",
     "BURN",
     "FLOOD",
     "CITADEL",
     "BASE_DEFENSE",
     "BASE_CAPTURE",
     "BASE_CAPTURE_ASSIST",
     "SUPPRESSED",
     "SECONDARY_CALIBER",
     "BUILDING_KILL",
     "DETECTED",
     "BOMB_OVER_PENETRATION",
     "BOMB_PENETRATION",
     "BOMB_NO_PENETRATION",
     "BOMB_RICOCHET",
     "ROCKET",
     "ROCKET_PENETRATION",
     "ROCKET_NO_PENETRATION",
     "SPLANE"
    ]
   }
  ],
  "successEventsCheckType": {},
  "successOnBattleEnd": false,
  "typeinfo": {
   "nation": "Common",
   "species": "IndividualTask",
   "type": "Other"
  }
 },
 {
  "caption": "PCOI020",
  "enabled": true,
  "failureEvents": [],
  "failureEventsCheckType": {},
  "id": 4273719216,
  "index": "PCOI020",
  "name": "PCOI020_RibbonsCitadel2",
  "restrictions": {
   "forbiddenShips": [
    "PBSB106_Queen_Elizabeth",
    "PBSB107_King_George_V",
    "PBSB108_Monarch",
    "PBSB517_Nelson",
    "PBSB527_Duke_of_York",
    "PASC206_Dallas",
    "PASC207_Helena",
    "PASC208_Cleveland",
    "PASC006_Atlanta_1942",
    "PASC597_Nueve_de_Julio_1951",
    "PVSC507_Nueve_de_Julio_1951",
    "PJSC007_Aoba_1943",
    "PJSC008_Myoko_1945",
    "PJSC009_Mogami_1935",
    "PJSC705_Myoko",
    "PJSC707_Ashigara",
    "PJSC709_Haguro",
    "PJSC737_Nachi",
    "PJSC717_Yellow_Dragon",
    "PJSC727_Blue_Dragon",
    "PJSC038_Atago_1944",
    "PJSC708_ARP_Takao",
    "PJSC598_Black_AtagoPGSC106_Nurnberg",
    "PRSC107_Schors",
    "PRSC108_Pr_68_Chapaev",
    "PRSC606_Admiral_Makarov",
    "PRSC518_Lazo",
    "PRSC508_Kutuzov_1952",
    "PZSC506_Huang_he",
    "PZSC508_Irian"
   ],
   "level": [
    6,
    7,
    8
   ],
   "specificShips": [
    "PASB705_Texas_1944",
    "PASC109_Buffalo"
   ],
   "subtype": [
    "Battleship",
    "Cruiser"
   ]
  },
  "successEvents": [
   {
    "count": 2,
    "gainer": "owner",
    "name": "RibbonGained",
    "ribbonType": [
     "CITADEL"
    ]
   }
  ],
  "successEventsCheckType": {},
  "successOnBattleEnd": false,
  "typeinfo": {
   "nation": "Common",
   "species": "IndividualTask",
   "type": "Other"
  }
 },
 {
  "caption": "PCOI022",
  "enabled": true,
  "failureEvents": [],
  "failureEventsCheckType": {},
  "id": 4271622064,
  "index": "PCOI022",
  "name": "PCOI022_RibbonsPlane8",
  "restrictions": {
   "level": [
    10
   ],
   "subtype": "AirCarrier"
  },
  "successEvents": [
   {
    "count": 8,
    "gainer": "owner",
    "name": "RibbonGained",
    "ribbonType": [
     "PLANE",
     "SPLANE"
    ]
   }
  ],
  "successEventsCheckType": {},
  "successOnBattleEnd": false,
  "typeinfo": {
   "nation": "Common",
   "species": "IndividualTask",
   "type": "Other"
  }
 },
 {
  "caption": "PCOI017",
  "enabled": true,
  "failureEvents": [],
  "failureEventsCheckType": {},
  "id": 4276864944,
  "index": "PCOI017",
  "name": "PCOI017_RibbonsATBA10",
  "restrictions": {
   "specificShips": [
    "PGSB506_Prinz_Eithel_Friedrich",
    "PGSB507_Scharnhorst",
    "PGSB107_Gneisenau",
    "PFSB108_Richelieu",
    "PFSB508_Gascogne",
    "PFSB518_Jean_Bart",
    "PFSB510_Bourgogne",
    "PJSB509_Musashi",
    "PJSB018_Yamato_1944"
   ]
  },
  "successEvents": [
   {
    "count": 10,
    "gainer": "owner",
    "name": "RibbonGained",
    "ribbonType": [
     "SECONDARY_CALIBER"
    ]
   }
  ],
  "successEventsCheckType": {},
  "successOnBattleEnd": false,
  "typeinfo": {
   "nation": "Common",
   "species": "IndividualTask",
   "type": "Other"
  }
 },
 {
  "caption": "PCOI012",
  "enabled": true,
  "failureEvents": [],
  "failureEventsCheckType": {},
  "id": 4282107824,
  "index": "PCOI012",
  "name": "PCOI012_Consumables4",
  "restrictions": {
   "forbiddenShips": "PRSB105_Pyotr_Velikiy",
   "level": [
    5
   ],
   "specificShips": [
    "PJSB507_Ashitaka",
    "PBSB517_Nelson",
    "PBSB508_Vanguard",
    "PFSB106_Normandie",
    "PFSB107_Lyon",
    "PGSB506_Prinz_Eithel_Friedrich",
    "PISB805_TST_CESARE",
    "PRSB107_Sinop",
    "PRSB108_Vladivostok",
    "PRSB518_Lenin",
    "PRSB109_Sovetsky_Soyuz"
   ],
   "subtype": [
    "Battleship",
    "Cruiser",
    "Destroyer"
   ]
  },
  "successEvents": [
   {
    "consumableType": [
     "crashCrew",
     "smokeGenerator",
     "speedBoosters",
     "scout",
     "fighter",
     "regenCrew",
     "airDefenseDisp",
     "sonar",
     "rls",
     "torpedoReloader",
     "artilleryBoosters"
    ],
    "count": 4,
    "name": "ConsumableUsed",
    "user": "owner"
   }
  ],
  "successEventsCheckType": {},
  "successOnBattleEnd": false,
  "typeinfo": {
   "nation": "Common",
   "species": "IndividualTask",
   "type": "Other"
  }
 },
 {
  "caption": "PCOI019",
  "enabled": true,
  "failureEvents": [],
  "failureEventsCheckType": {},
  "id": 4274767792,
  "index": "PCOI019",
  "name": "PCOI019_RibbonsCitadel3",
  "restrictions": {
   "forbiddenShips": [
    "PBSB109_Lion",
    "PBSB110_Conqueror"
   ],
   "level": [
    9,
    10
   ],
   "specificShips": [
    "PASC020_Des_Moines_1948",
    "PFSC110_Henri_IV",
    "PRSC110_Pr_66_Moskva",
    "PASC510_Alaska",
    "PASC710_Salem",
    "PJSC510_Azumaya",
    "PRSC509_Kronshtadt",
    "PRSC510_Stalingrad"
   ],
   "subtype": "Battleship"
  },
  "successEvents": [
   {
    "count": 3,
    "gainer": "owner",
    "name": "RibbonGained",
    "ribbonType": [
     "CITADEL"
    ]
   }
  ],
  "successEventsCheckType": {},
  "successOnBattleEnd": false,
  "typeinfo": {
   "nation": "Common",
   "species": "IndividualTask",
   "type": "Other"
  }
 },
 {
  "caption": "PCOI007",
  "enabled": true,
  "failureEvents": [],
  "failureEventsCheckType": {},
  "id": 4287350704,
  "index": "PCOI007",
  "name": "PCOI007_Ribbons60",
  "restrictions": {
   "forbiddenShips": [
    "PBSC110_Minotaur",
    "PJSD108_Akizuki",
    "PJSD219_Kitakaze",
    "PJSD210_Harugumo",
    "PASC210_Worcester",
    "PRSD110_Pr_24_Khabarovsk",
    "PBSD110_Daring"
   ],
   "specificShips": [
    "PGSB110_Grossdeutschland",
    "PASB518_Massachusetts",
    "PASB598_Black_Massachusetts"
   ],
   "subtype": [
    "Cruiser",
    "Destroyer"
   ]
  },
  "successEvents": [
   {
    "count": 60,
    "gainer": "owner",
    "name": "RibbonGained",
    "ribbonType": [
     "MAIN_CALIBER_OVER_PENETRATION",
     "MAIN_CALIBER_PENETRATION",
     "MAIN_CALIBER_NO_PENETRATION",
     "MAIN_CALIBER_RICOCHET",
     "TORPEDO",
     "BOMB",
     "PLANE",
     "CRIT",
     "FRAG",
     "BURN",
     "FLOOD",
     "CITADEL",
     "BASE_DEFENSE",
     "BASE_CAPTURE",
     "BASE_CAPTURE_ASSIST",
     "SUPPRESSED",
     "SECONDARY_CALIBER",
     "BUILDING_KILL",
     "DETECTED",
     "BOMB_OVER_PENETRATION",
     "BOMB_PENETRATION",
     "BOMB_NO_PENETRATION",
     "BOMB_RICOCHET",
     "ROCKET",
     "ROCKET_PENETRATION",
     "ROCKET_NO_PENETRATION",
     "SPLANE"
    ]
   }
  ],
  "successEventsCheckType": {},
  "successOnBattleEnd": false,
  "typeinfo": {
   "nation": "Common",
   "species": "IndividualTask",
   "type": "Other"
  }
 },
 {
  "caption": "PCOI016",
  "enabled": true,
  "failureEvents": [],
  "failureEventsCheckType": {},
  "id": 4277913520,
  "index": "PCOI016",
  "name": "PCOI016_RibbonsATBA30",
  "restrictions": {
   "specificShips": [
    "PGSB108_Bismarck",
    "PGSB002_Tirpiz_1942",
    "PGSB598_Black_Tirpitz",
    "PGSB109_Friedrich_der_Grosse",
    "PGSB110_Grossdeutschland",
    "PASB518_Massachusetts",
    "PASB598_Black_Massachusetts",
    "PFSB109_Alsace",
    "PFSB110_France"
   ]
  },
  "successEvents": [
   {
    "count": 30,
    "gainer": "owner",
    "name": "RibbonGained",
    "ribbonType": [
     "SECONDARY_CALIBER"
    ]
   }
  ],
  "successEventsCheckType": {},
  "successOnBattleEnd": false,
  "typeinfo": {
   "nation": "Common",
   "species": "IndividualTask",
   "type": "Other"
  }
 },
 {
  "caption": "PCOI014",
  "enabled": true,
  "failureEvents": [],
  "failureEventsCheckType": {},
  "id": 4280010672,
  "index": "PCOI014",
  "name": "PCOI014_TorpedoSpot6",
  "restrictions": {
   "level": [
    7,
    8,
    9
   ],
   "subtype": "Destroyer"
  },
  "successEvents": [
   {
    "count": 6,
    "isAviaTorpedo": null,
    "name": "TorpedoSpotted",
    "spotter": "owner"
   }
  ],
  "successEventsCheckType": {},
  "successOnBattleEnd": false,
  "typeinfo": {
   "nation": "Common",
   "species": "IndividualTask",
   "type": "Other"
  }
 },
 {
  "caption": "PCOI004",
  "enabled": true,
  "failureEvents": [],
  "failureEventsCheckType": {},
  "id": 4290496432,
  "index": "PCOI004",
  "name": "PCOI004_Detected3",
  "restrictions": {
   "subtype": "Destroyer"
  },
  "successEvents": [
   {
    "count": 3,
    "gainer": "owner",
    "name": "RibbonGained",
    "ribbonType": [
     "DETECTED"
    ]
   }
  ],
  "successEventsCheckType": {},
  "successOnBattleEnd": false,
  "typeinfo": {
   "nation": "Common",
   "species": "IndividualTask",
   "type": "Other"
  }
 },
 {
  "caption": "PCOI024",
  "enabled": true,
  "failureEvents": [],
  "failureEventsCheckType": {},
  "id": 4269524912,
  "index": "PCOI024",
  "name": "PCOI024_RibbonsPlane3",
  "restrictions": {
   "level": [
    6
   ],
   "subtype": "AirCarrier"
  },
  "successEvents": [
   {
    "count": 3,
    "gainer": "owner",
    "name": "RibbonGained",
    "ribbonType": [
     "PLANE",
     "SPLANE"
    ]
   }
  ],
  "successEventsCheckType": {},
  "successOnBattleEnd": false,
  "typeinfo": {
   "nation": "Common",
   "species": "IndividualTask",
   "type": "Other"
  }
 },
 {
  "caption": "PCOI013",
  "enabled": true,
  "failureEvents": [],
  "failureEventsCheckType": {},
  "id": 4281059248,
  "index": "PCOI013",
  "name": "PCOI013_TorpedoSpot8",
  "restrictions": {
   "level": [
    10
   ],
   "subtype": "Destroyer"
  },
  "successEvents": [
   {
    "count": 8,
    "isAviaTorpedo": null,
    "name": "TorpedoSpotted",
    "spotter": "owner"
   }
  ],
  "successEventsCheckType": {},
  "successOnBattleEnd": false,
  "typeinfo": {
   "nation": "Common",
   "species": "IndividualTask",
   "type": "Other"
  }
 },
 {
  "caption": "PCOI011",
  "enabled": true,
  "failureEvents": [],
  "failureEventsCheckType": {},
  "id": 4283156400,
  "index": "PCOI011",
  "name": "PCOI011_Consumables5",
  "restrictions": {
   "forbiddenShips": [
    "PJSD108_Akizuki",
    "PJSD518_Asashio",
    "PJSD598_Black_Asashio",
    "PJSC038_Atago_1944",
    "PJSC708_ARP_Takao",
    "PJSC598_Black_Atago",
    "PASD506_Monaghan",
    "PASD508_Kidd",
    "PASC206_Dallas",
    "PASC207_Helena",
    "PASC208_Cleveland",
    "PRSD208_Pr_30",
    "PGSD506_T_61",
    "PGSD508_Z_39",
    "PGSC506_Admiral_Graf_Spee",
    "PGSC706_HSF_Graf_Spee",
    "PGSC508_Prinz_Eugen",
    "PGSB108_Bismarck",
    "PBSC107_Fiji",
    "PBSC108_Edinburgh",
    "PBSD517_Cossack",
    "PFSB508_Gascogne",
    "PFSC106_La_Galissonniere",
    "PFSC107_Algerie",
    "PFSC108_Charles_Martel",
    "PFSC506_De_Grasse",
    "PUSD507_Haida",
    "PISC506_DucadAosta",
    "PISC507_Duca_degli_Abruzzi",
    "PJSB507_Ashitaka",
    "PBSB517_Nelson",
    "PBSB508_Vanguard",
    "PFSB106_Normandie",
    "PFSB107_Lyon",
    "PGSB506_Prinz_Eithel_Friedrich",
    "PISB805_TST_CESARE",
    "PRSB106_Izmail",
    "PRSB107_Sinop",
    "PRSB108_Vladivostok",
    "PRSB518_Lenin"
   ],
   "level": [
    6,
    7,
    8
   ],
   "subtype": [
    "Battleship",
    "Cruiser",
    "Destroyer"
   ]
  },
  "successEvents": [
   {
    "consumableType": [
     "crashCrew",
     "smokeGenerator",
     "speedBoosters",
     "scout",
     "fighter",
     "regenCrew",
     "airDefenseDisp",
     "sonar",
     "rls",
     "torpedoReloader",
     "artilleryBoosters"
    ],
    "count": 5,
    "name": "ConsumableUsed",
    "user": "owner"
   }
  ],
  "successEventsCheckType": {},
  "successOnBattleEnd": false,
  "typeinfo": {
   "nation": "Common",
   "species": "IndividualTask",
   "type": "Other"
  }
 },
 {
  "caption": "PCOI018",
  "enabled": true,
  "failureEvents": [],
  "failureEventsCheckType": {},
  "id": 4275816368,
  "index": "PCOI018",
  "name": "PCOI018_DestroyModules",
  "restrictions": {
   "subtype": [
    "AirCarrier",
    "Battleship",
    "Cruiser"
   ]
  },
  "successEvents": [
   {
    "count": 5,
    "damager": "owner",
    "moduleType": [
     "Artillery",
     "AirDefense",
     "ATBA",
     "Engine",
     "SteeringGear",
     "Torpedoes"
    ],
    "name": [
     "ModuleCrited",
     "ModuleDestroyed"
    ],
    "victim": {
     "entityClass": [
      "AirCarrier",
      "Auxiliary",
      "Battleship",
      "Cruiser",
      "Destroyer"
     ],
     "team": "enemy"
    }
   }
  ],
  "successEventsCheckType": {},
  "successOnBattleEnd": false,
  "typeinfo": {
   "nation": "Common",
   "species": "IndividualTask",
   "type": "Other"
  }
 },
 {
  "caption": "PCOI009",
  "enabled": true,
  "failureEvents": [],
  "failureEventsCheckType": {},
  "id": 4285253552,
  "index": "PCOI009",
  "name": "PCOI009_Ribbons30",
  "restrictions": {
   "forbiddenShips": [
    "PASB518_Massachusetts",
    "PASB598_Black_Massachusetts",
    "PJSB006_Fuso_1943",
    "PGSB507_Scharnhorst",
    "PGSB002_Tirpiz_1942",
    "PGSB598_Black_Tirpitz",
    "PGSB108_Bismarck",
    "PFSB108_Richelieu",
    "PFSB508_Gascogne"
   ],
   "level": [
    5,
    6,
    7,
    8
   ],
   "subtype": [
    "Battleship",
    "AirCarrier"
   ]
  },
  "successEvents": [
   {
    "count": 30,
    "gainer": "owner",
    "name": "RibbonGained",
    "ribbonType": [
     "MAIN_CALIBER_OVER_PENETRATION",
     "MAIN_CALIBER_PENETRATION",
     "MAIN_CALIBER_NO_PENETRATION",
     "MAIN_CALIBER_RICOCHET",
     "TORPEDO",
     "BOMB",
     "PLANE",
     "CRIT",
     "FRAG",
     "BURN",
     "FLOOD",
     "CITADEL",
     "BASE_DEFENSE",
     "BASE_CAPTURE",
     "BASE_CAPTURE_ASSIST",
     "SUPPRESSED",
     "SECONDARY_CALIBER",
     "BUILDING_KILL",
     "DETECTED",
     "BOMB_OVER_PENETRATION",
     "BOMB_PENETRATION",
     "BOMB_NO_PENETRATION",
     "BOMB_RICOCHET",
     "ROCKET",
     "ROCKET_PENETRATION",
     "ROCKET_NO_PENETRATION",
     "SPLANE"
    ]
   }
  ],
  "successEventsCheckType": {},
  "successOnBattleEnd": false,
  "typeinfo": {
   "nation": "Common",
   "species": "IndividualTask",
   "type": "Other"
  }
 },
 {
  "caption": "PCOI008",
  "enabled": true,
  "failureEvents": [],
  "failureEventsCheckType": {},
  "id": 4286302128,
  "index": "PCOI008",
  "name": "PCOI008_Ribbons45",
  "restrictions": {
   "forbiddenShips": "PGSB110_Grossdeutschland",
   "level": [
    9,
    10
   ],
   "specificShips": [
    "PJSB006_Fuso_1943",
    "PGSB507_Scharnhorst",
    "PGSB002_Tirpiz_1942",
    "PGSB598_Black_Tirpitz",
    "PGSB108_Bismarck",
    "PFSB108_Richelieu",
    "PFSB508_Gascogne"
   ],
   "subtype": [
    "Battleship",
    "AirCarrier"
   ]
  },
  "successEvents": [
   {
    "count": 45,
    "gainer": "owner",
    "name": "RibbonGained",
    "ribbonType": [
     "MAIN_CALIBER_OVER_PENETRATION",
     "MAIN_CALIBER_PENETRATION",
     "MAIN_CALIBER_NO_PENETRATION",
     "MAIN_CALIBER_RICOCHET",
     "TORPEDO",
     "BOMB",
     "PLANE",
     "CRIT",
     "FRAG",
     "BURN",
     "FLOOD",
     "CITADEL",
     "BASE_DEFENSE",
     "BASE_CAPTURE",
     "BASE_CAPTURE_ASSIST",
     "SUPPRESSED",
     "SECONDARY_CALIBER",
     "BUILDING_KILL",
     "DETECTED",
     "BOMB_OVER_PENETRATION",
     "BOMB_PENETRATION",
     "BOMB_NO_PENETRATION",
     "BOMB_RICOCHET",
     "ROCKET",
     "ROCKET_PENETRATION",
     "ROCKET_NO_PENETRATION",
     "SPLANE"
    ]
   }
  ],
  "successEventsCheckType": {},
  "successOnBattleEnd": false,
  "typeinfo": {
   "nation": "Common",
   "species": "IndividualTask",
   "type": "Other"
  }
 },
 {
  "caption": "PCOI021",
  "enabled": true,
  "failureEvents": [],
  "failureEventsCheckType": {},
  "id": 4272670640,
  "index": "PCOI021",
  "name": "PCOI021_RibbonsFlood1",
  "restrictions": {
   "forbiddenShips": [
    "PBSA508_Indomitable",
    "PJSD518_Asashio",
    "PJSD598_Black_Asashio",
    "PASD005_Farragut_1944",
    "PRSD206_Pr_7",
    "PRSD207_Minsk",
    "PRSD308_Pr_48",
    "PRSD409_Pr_20i_Tashkent",
    "PRSD110_Pr_24_Khabarovsk"
   ],
   "level": [
    6,
    7,
    8,
    9,
    10
   ],
   "subtype": [
    "AirCarrier",
    "Destroyer"
   ]
  },
  "successEvents": [
   {
    "count": 1,
    "gainer": "owner",
    "name": "RibbonGained",
    "ribbonType": [
     "FLOOD"
    ]
   }
  ],
  "successEventsCheckType": {},
  "successOnBattleEnd": false,
  "typeinfo": {
   "nation": "Common",
   "species": "IndividualTask",
   "type": "Other"
  }
 },
 {
  "caption": "PCOI005",
  "enabled": true,
  "failureEvents": [],
  "failureEventsCheckType": {},
  "id": 4289447856,
  "index": "PCOI005",
  "name": "PCOI005_Detected2",
  "restrictions": {
   "subtype": "Cruiser"
  },
  "successEvents": [
   {
    "count": 2,
    "gainer": "owner",
    "name": "RibbonGained",
    "ribbonType": [
     "DETECTED"
    ]
   }
  ],
  "successEventsCheckType": {},
  "successOnBattleEnd": false,
  "typeinfo": {
   "nation": "Common",
   "species": "IndividualTask",
   "type": "Other"
  }
 },
 {
  "caption": "PCOI010",
  "enabled": true,
  "failureEvents": [],
  "failureEventsCheckType": {},
  "id": 4284204976,
  "index": "PCOI010",
  "name": "PCOI010_Consumables6",
  "restrictions": {
   "forbiddenShips": [
    "PRSB109_Sovetsky_Soyuz",
    "PRSB110_Sovetskaya_Rossiya",
    "PRSB510_Pobeda"
   ],
   "level": [
    9,
    10
   ],
   "specificShips": [
    "PJSD108_Akizuki",
    "PJSD518_Asashio",
    "PJSD598_Black_Asashio",
    "PJSC038_Atago_1944",
    "PJSC708_ARP_Takao",
    "PJSC598_Black_Atago",
    "PASD506_Monaghan",
    "PASD508_Kidd",
    "PASC206_Dallas",
    "PASC207_Helena",
    "PASC208_Cleveland",
    "PRSD208_Pr_30",
    "PGSD506_T_61",
    "PGSD508_Z_39",
    "PGSC506_Admiral_Graf_Spee",
    "PGSC706_HSF_Graf_Spee",
    "PGSC508_Prinz_Eugen",
    "PGSB108_Bismarck",
    "PBSC107_Fiji",
    "PBSC108_Edinburgh",
    "PBSD517_Cossack",
    "PFSB508_Gascogne",
    "PFSC106_La_Galissonniere",
    "PFSC107_Algerie",
    "PFSC108_Charles_Martel",
    "PFSC506_De_Grasse",
    "PUSD507_Haida",
    "PISC506_DucadAosta",
    "PISC507_Duca_degli_Abruzzi"
   ],
   "subtype": [
    "Battleship",
    "Cruiser",
    "Destroyer"
   ]
  },
  "successEvents": [
   {
    "consumableType": [
     "crashCrew",
     "smokeGenerator",
     "speedBoosters",
     "scout",
     "fighter",
     "regenCrew",
     "airDefenseDisp",
     "sonar",
     "rls",
     "torpedoReloader",
     "artilleryBoosters"
    ],
    "count": 6,
    "name": "ConsumableUsed",
    "user": "owner"
   }
  ],
  "successEventsCheckType": {},
  "successOnBattleEnd": false,
  "typeinfo": {
   "nation": "Common",
   "species": "IndividualTask",
   "type": "Other"
  }
 },
 {
  "caption": "PCOI001",
  "enabled": true,
  "failureEvents": [],
  "failureEventsCheckType": {},
  "id": 4293642160,
  "index": "PCOI001",
  "name": "PCOI001_RibbonsFire4",
  "restrictions": {
   "forbiddenShips": [
    "PBSC105_Emerald",
    "PBSC106_Leander",
    "PBSC107_Fiji",
    "PBSC108_Edinburgh",
    "PBSC109_Neptune",
    "PBSC110_Minotaur"
   ],
   "specificShips": [
    "PASA110_Midway",
    "PBSB105_Iron_Duke",
    "PBSB107_King_George_V",
    "PBSB517_Nelson",
    "PBSB527_Duke_of_York",
    "PBSB108_Monarch",
    "PBSB109_Lion",
    "PBSB110_Conqueror"
   ],
   "subtype": "Cruiser"
  },
  "successEvents": [
   {
    "count": 4,
    "gainer": "owner",
    "name": "RibbonGained",
    "ribbonType": [
     "BURN"
    ]
   }
  ],
  "successEventsCheckType": {},
  "successOnBattleEnd": false,
  "typeinfo": {
   "nation": "Common",
   "species": "IndividualTask",
   "type": "Other"
  }
 },
 {
  "caption": "PCOI015",
  "enabled": true,
  "failureEvents": [],
  "failureEventsCheckType": {},
  "id": 4278962096,
  "index": "PCOI015",
  "name": "PCOI015_TorpedoSpot4",
  "restrictions": {
   "level": [
    5,
    6
   ],
   "subtype": "Destroyer"
  },
  "successEvents": [
   {
    "count": 4,
    "isAviaTorpedo": null,
    "name": "TorpedoSpotted",
    "spotter": "owner"
   }
  ],
  "successEventsCheckType": {},
  "successOnBattleEnd": false,
  "typeinfo": {
   "nation": "Common",
   "species": "IndividualTask",
   "type": "Other"
  }
 },
 {
  "caption": "PCOI003",
  "enabled": true,
  "failureEvents": [],
  "failureEventsCheckType": {},
  "id": 4291545008,
  "index": "PCOI003",
  "name": "PCOI003_Detected9",
  "restrictions": {
   "subtype": "AirCarrier"
  },
  "successEvents": [
   {
    "count": 7,
    "gainer": "owner",
    "name": "RibbonGained",
    "ribbonType": [
     "DETECTED"
    ]
   }
  ],
  "successEventsCheckType": {},
  "successOnBattleEnd": false,
  "typeinfo": {
   "nation": "Common",
   "species": "IndividualTask",
   "type": "Other"
  }
 }
]