[
 {
  "antiAirAuraDistance": 67.0,
  "antiAirAuraStrength": 0.061,
  "id": 4273989584,
  "index": "PBGA020",
  "name": "PBGA020_20mm_Oerlikon_MK_V",
  "numBarrels": 2,
  "shotDelay": 5.0,
  "typeinfo": {
   "nation": "United_Kingdom",
   "species": "AAircraft",
   "type": "Gun"
  }
 },
 {
  "antiAirAuraDistance": 117.0,
  "antiAirAuraStrength": 0.202,
  "id": 4260358096,
  "index": "PBGA033",
  "name": "PBGA033_40mm_Bofors_MK_VI",
  "numBarrels": 6,
  "shotDelay": 5.0,
  "typeinfo": {
   "nation": "United_Kingdom",
   "species": "AAircraft",
   "type": "Gun"
  }
 },
 {
  "ammoList": [
   "PBPA041_134MM_MI_HE"
  ],
  "antiAirAuraDistance": 150.0,
  "antiAirAuraStrength": 0.081,
  "barrelDiameter": 0.133,
  "delim": 0.6,
  "id": 3733383120,
  "idealDistance": 333.333,
  "idealRadius": 20,
  "index": "PBGS535",
  "minRadius": 1.0,
  "name": "PBGS535_QF_5_2in_MkI",
  "radiusOnDelim": 0.8,
  "radiusOnMax": 1.0,
  "radiusOnZero": 0.1,
  "rotationSpeed": [
   60.0,
   1.0
  ],
  "shotDelay": 6.67,
  "smokePenalty": 0.0001,
  "typeinfo": {
   "nation": "United_Kingdom",
   "species": "Secondary",
   "type": "Gun"
  },
  "vertSector": [
   -1.0,
   70.0
  ]
 },
 {
  "deadZone": [],
  "id": 4285130704,
  "index": "PBGM009",
  "name": "PBGM009_15in42_MK1",
  "typeinfo": {
   "nation": "United_Kingdom",
   "species": "Main",
   "type": "Gun"
  }
 },
 {
  "deadZone": [],
  "id": 4266256336,
  "index": "PBGM027",
  "name": "PBGM027_4in50_Mk12",
  "typeinfo": {
   "nation": "United_Kingdom",
   "species": "Main",
   "type": "Gun"
  }
 },
 {
  "ammoList": [
   "PBPA036_114MM_MII_HE"
  ],
  "antiAirAuraDistance": 167.0,
  "antiAirAuraStrength": 0.089,
  "barrelDiameter": 0.113,
  "delim": 0.6,
  "id": 4220970960,
  "idealDistance": 333.333,
  "idealRadius": 20,
  "index": "PBGS070",
  "minRadius": 1.0,
  "name": "PBGS070_114mm_45_MKIII",
  "radiusOnDelim": 0.8,
  "radiusOnMax": 1.0,
  "radiusOnZero": 0.1,
  "rotationSpeed": [
   60.0,
   60.0
  ],
  "shotDelay": 5.0,
  "smokePenalty": 0.0001,
  "typeinfo": {
   "nation": "United_Kingdom",
   "species": "Secondary",
   "type": "Gun"
  },
  "vertSector": [
   -1.0,
   80.0
  ]
 },
 {
  "ammoList": [
   "PCPA001_Shell"
  ],
  "antiAirAuraDistance": -1.0,
  "antiAirAuraStrength": -1.0,
  "barrelDiameter": 20,
  "delim": 0.6,
  "id": 3753306064,
  "idealDistance": 333.333,
  "idealRadius": 20,
  "index": "PBGS516",
  "minRadius": 1.0,
  "name": "PBGS516_5_25in_50_QF_MK_I_Ice",
  "radiusOnDelim": 0.8,
  "radiusOnMax": 1.0,
  "radiusOnZero": 0.1,
  "rotationSpeed": [
   60.0,
   1.0
  ],
  "shotDelay": 5.0,
  "smokePenalty": 0.0001,
  "typeinfo": {
   "nation": "United_Kingdom",
   "species": "Secondary",
   "type": "Gun"
  },
  "vertSector": [
   -1.0,
   90.0
  ]
 },
 {
  "deadZone": [],
  "id": 4267304912,
  "index": "PBGM026",
  "name": "PBGM026_4in50_Mk12",
  "typeinfo": {
   "nation": "United_Kingdom",
   "species": "Main",
   "type": "Gun"
  }
 },
 {
  "deadZone": [],
  "id": 4269402064,
  "index": "PBGM024",
  "name": "PBGM024_6in50_QF_Mk_V",
  "typeinfo": {
   "nation": "United_Kingdom",
   "species": "Main",
   "type": "Gun"
  }
 },
 {
  "ammoList": [
   "PBPA070_140MM_HE_BL_MKI"
  ],
  "antiAirAuraDistance": 0.0,
  "antiAirAuraStrength": 0.0,
  "barrelDiameter": 0.14,
  "delim": 0.6,
  "id": 4190562256,
  "idealDistance": 333.333,
  "idealRadius": 20,
  "index": "PBGS099",
  "minRadius": 1.0,
  "name": "PBGS099_5_5in_Mk1",
  "radiusOnDelim": 0.8,
  "radiusOnMax": 1.0,
  "radiusOnZero": 0.1,
  "rotationSpeed": [
   60.0,
   1.0
  ],
  "shotDelay": 5.0,
  "smokePenalty": 0.0001,
  "typeinfo": {
   "nation": "United_Kingdom",
   "species": "Secondary",
   "type": "Gun"
  },
  "vertSector": [
   -1.0,
   25.0
  ]
 },
 {
  "antiAirAuraDistance": 117.0,
  "antiAirAuraStrength": 0.159,
  "id": 4282378192,
  "index": "PBGA012",
  "name": "PBGA012_40mm_Bofors_Mk2",
  "numBarrels": 4,
  "shotDelay": 5.0,
  "typeinfo": {
   "nation": "United_Kingdom",
   "species": "AAircraft",
   "type": "Gun"
  }
 },
 {
  "deadZone": [],
  "id": 4253673424,
  "index": "PBGM039",
  "name": "PBGM039_234mm50_Mk_XII_Twin",
  "typeinfo": {
   "nation": "United_Kingdom",
   "species": "Main",
   "type": "Gun"
  }
 },
 {
  "deadZone": [],
  "id": 4201244624,
  "index": "PBGM089",
  "name": "PBGM089_4_7in_45_BL_MKI",
  "typeinfo": {
   "nation": "United_Kingdom",
   "species": "Main",
   "type": "Gun"
  }
 },
 {
  "ammoList": [
   "PBPA004_102mm_HE_HE_35lbs"
  ],
  "antiAirAuraDistance": 167.0,
  "antiAirAuraStrength": 0.15,
  "barrelDiameter": 0.102,
  "delim": 0.6,
  "id": 4088850384,
  "idealDistance": 333.333,
  "idealRadius": 20,
  "index": "PBGS196",
  "minRadius": 1.0,
  "name": "PBGS196_4IN45_XX",
  "radiusOnDelim": 0.8,
  "radiusOnMax": 1.0,
  "radiusOnZero": 0.1,
  "rotationSpeed": [
   60.0,
   1.0
  ],
  "shotDelay": 3.0,
  "smokePenalty": 0.0001,
  "typeinfo": {
   "nation": "United_Kingdom",
   "species": "Secondary",
   "type": "Gun"
  },
  "vertSector": [
   -1.0,
   80.0
  ]
 },
 {
  "antiAirAuraDistance": 33.0,
  "antiAirAuraStrength": 0.016,
  "id": 4164937680,
  "index": "PBGA124",
  "name": "PBGA124_303_Lewis",
  "numBarrels": 1,
  "shotDelay": 5.0,
  "typeinfo": {
   "nation": "United_Kingdom",
   "species": "AAircraft",
   "type": "Gun"
  }
 },
 {
  "ammoList": [
   "PBPA077_152MM_ATBA_HE"
  ],
  "antiAirAuraDistance": 0.0,
  "antiAirAuraStrength": 0.0,
  "barrelDiameter": 0.152,
  "delim": 0.6,
  "id": 4223068112,
  "idealDistance": 333.333,
  "idealRadius": 20,
  "index": "PBGS068",
  "minRadius": 1.0,
  "name": "PBGS068_6in_50_BL_MkXXII_MkXVIII",
  "radiusOnDelim": 0.8,
  "radiusOnMax": 1.0,
  "radiusOnZero": 0.1,
  "rotationSpeed": [
   60.0,
   1.0
  ],
  "shotDelay": 12.0,
  "smokePenalty": 0.0001,
  "typeinfo": {
   "nation": "United_Kingdom",
   "species": "Secondary",
   "type": "Gun"
  },
  "vertSector": [
   -1.0,
   60.0
  ]
 },
 {
  "ammoList": [
   "PBPA004_102mm_HE_HE_35lbs"
  ],
  "antiAirAuraDistance": 167.0,
  "antiAirAuraStrength": 0.094,
  "barrelDiameter": 0.102,
  "delim": 0.6,
  "id": 4288079824,
  "idealDistance": 333.333,
  "idealRadius": 20,
  "index": "PBGS006",
  "minRadius": 1.0,
  "name": "PBGS006_4in45_QF_Mk_XIX",
  "radiusOnDelim": 0.8,
  "radiusOnMax": 1.0,
  "radiusOnZero": 0.1,
  "rotationSpeed": [
   60.0,
   1.0
  ],
  "shotDelay": 3.0,
  "smokePenalty": 0.0001,
  "typeinfo": {
   "nation": "United_Kingdom",
   "species": "Secondary",
   "type": "Gun"
  },
  "vertSector": [
   -1.0,
   80.0
  ]
 },
 {
  "antiAirAuraDistance": -1.0,
  "antiAirAuraStrength": -1.0,
  "id": 3754944464,
  "index": "PBGA515",
  "name": "PBGA515_20mm_Oerlikon_MK4_Ice",
  "numBarrels": 2,
  "shotDelay": 5.0,
  "typeinfo": {
   "nation": "United_Kingdom",
   "species": "AAircraft",
   "type": "Gun"
  }
 },
 {
  "ammoList": [
   "PBPA019_114MM_HE_MK16"
  ],
  "antiAirAuraDistance": 167.0,
  "antiAirAuraStrength": 0.149,
  "barrelDiameter": 0.113,
  "delim": 0.6,
  "id": 4160153552,
  "idealDistance": 333.333,
  "idealRadius": 20,
  "index": "PBGS128",
  "minRadius": 1.0,
  "name": "PBGS128_4_5in_45_Mk4_2barrels",
  "radiusOnDelim": 0.8,
  "radiusOnMax": 1.0,
  "radiusOnZero": 0.1,
  "rotationSpeed": [
   60.0,
   1.0
  ],
  "shotDelay": 5.0,
  "smokePenalty": 0.0001,
  "typeinfo": {
   "nation": "United_Kingdom",
   "species": "Secondary",
   "type": "Gun"
  },
  "vertSector": [
   -1.0,
   80.0
  ]
 },
 {
  "ammoList": [
   "PBPA003_152mm_HE_HE4crh"
  ],
  "antiAirAuraDistance": 0.0,
  "antiAirAuraStrength": 0.0,
  "barrelDiameter": 0.152,
  "delim": 0.6,
  "id": 4154910672,
  "idealDistance": 333.333,
  "idealRadius": 12.0,
  "index": "PBGS133",
  "minRadius": 1.0,
  "name": "PBGS133_6in50_MK13_Deck",
  "radiusOnDelim": 0.8,
  "radiusOnMax": 1.0,
  "radiusOnZero": 0.1,
  "rotationSpeed": [
   60.0,
   1.0
  ],
  "shotDelay": 5.0,
  "smokePenalty": 0.0001,
  "typeinfo": {
   "nation": "United_Kingdom",
   "species": "Secondary",
   "type": "Gun"
  },
  "vertSector": [
   -3.0,
   15.0
  ]
 },
 {
  "deadZone": [],
  "id": 4188661712,
  "index": "PBGM101",
  "name": "PBGM101_15in42_MK1_Vanguard",
  "typeinfo": {
   "nation": "United_Kingdom",
   "species": "Main",
   "type": "Gun"
  }
 },
 {
  "deadZone": [],
  "id": 4293519312,
  "index": "PBGM001",
  "name": "PBGM001_6in50_MK_XXIII",
  "typeinfo": {
   "nation": "United_Kingdom",
   "species": "Main",
   "type": "Gun"
  }
 },
 {
  "deadZone": [],
  "id": 4284082128,
  "index": "PBGM010",
  "name": "PBGM010_15in42_MK1_RF",
  "typeinfo": {
   "nation": "United_Kingdom",
   "species": "Main",
   "type": "Gun"
  }
 },
 {
  "ammoList": [
   "PBPT008_533_MKIX2"
  ],
  "barrelDiameter": 0.533,
  "id": 4245055440,
  "index": "PBGT047",
  "name": "PBGT047_21in_3tube_TR_Mk_IV_L",
  "numBarrels": 3,
  "rotationSpeed": [
   25.0,
   25.0
  ],
  "shotDelay": 72.0,
  "torpedoAngles": [
   2.4,
   3.6
  ],
  "typeinfo": {
   "nation": "United_Kingdom",
   "species": "Torpedo",
   "type": "Gun"
  }
 },
 {
  "deadZone": [],
  "id": 4163495888,
  "index": "PBGM125",
  "name": "PBGM125_8in50_MK1",
  "typeinfo": {
   "nation": "United_Kingdom",
   "species": "Main",
   "type": "Gun"
  }
 },
 {
  "deadZone": [],
  "id": 4213827536,
  "index": "PBGM077",
  "name": "PBGM077_16in_45_MkII_Cubic",
  "typeinfo": {
   "nation": "United_Kingdom",
   "species": "Main",
   "type": "Gun"
  }
 },
 {
  "deadZone": [],
  "id": 4244236240,
  "index": "PBGM048",
  "name": "PBGM048_15in42_MK2",
  "typeinfo": {
   "nation": "United_Kingdom",
   "species": "Main",
   "type": "Gun"
  }
 },
 {
  "antiAirAuraDistance": -1.0,
  "antiAirAuraStrength": -1.0,
  "id": 3757041616,
  "index": "PBGA513",
  "name": "PBGA513_2_pdr_MkVIII_8barrel_Ice",
  "numBarrels": 2,
  "shotDelay": 5.0,
  "typeinfo": {
   "nation": "United_Kingdom",
   "species": "AAircraft",
   "type": "Gun"
  }
 },
 {
  "deadZone": [],
  "id": 4159301584,
  "index": "PBGM129",
  "name": "PBGM129_8in50_BL_Mk8",
  "typeinfo": {
   "nation": "United_Kingdom",
   "species": "Main",
   "type": "Gun"
  }
 },
 {
  "deadZone": [],
  "id": 4185515984,
  "index": "PBGM104",
  "name": "PBGM104_12in45_MkX",
  "typeinfo": {
   "nation": "United_Kingdom",
   "species": "Main",
   "type": "Gun"
  }
 },
 {
  "ammoList": [
   "PBPA041_134MM_MI_HE"
  ],
  "antiAirAuraDistance": 150.0,
  "antiAirAuraStrength": 0.081,
  "barrelDiameter": 0.133,
  "delim": 0.6,
  "id": 4236699600,
  "idealDistance": 333.333,
  "idealRadius": 20,
  "index": "PBGS055",
  "minRadius": 1.0,
  "name": "PBGS055_5_25in_50_QF_MK_I",
  "radiusOnDelim": 0.8,
  "radiusOnMax": 1.0,
  "radiusOnZero": 0.1,
  "rotationSpeed": [
   60.0,
   1.0
  ],
  "shotDelay": 6.67,
  "smokePenalty": 0.0001,
  "typeinfo": {
   "nation": "United_Kingdom",
   "species": "Secondary",
   "type": "Gun"
  },
  "vertSector": [
   -1.0,
   70.0
  ]
 },
 {
  "deadZone": [],
  "id": 4189710288,
  "index": "PBGM100",
  "name": "PBGM100_4in_40_QF_MkIV",
  "typeinfo": {
   "nation": "United_Kingdom",
   "species": "Main",
   "type": "Gun"
  }
 },
 {
  "ammoList": [
   "PBPA003_152mm_HE_HE4crh"
  ],
  "antiAirAuraDistance": 0.0,
  "antiAirAuraStrength": 0.0,
  "barrelDiameter": 0.152,
  "delim": 0.6,
  "id": 4155959248,
  "idealDistance": 333.333,
  "idealRadius": 12.0,
  "index": "PBGS132",
  "minRadius": 1.0,
  "name": "PBGS132_6in50_MK13_Casemate",
  "radiusOnDelim": 0.8,
  "radiusOnMax": 1.0,
  "radiusOnZero": 0.1,
  "rotationSpeed": [
   60.0,
   1.0
  ],
  "shotDelay": 5.0,
  "smokePenalty": 0.0001,
  "typeinfo": {
   "nation": "United_Kingdom",
   "species": "Secondary",
   "type": "Gun"
  },
  "vertSector": [
   -3.0,
   15.0
  ]
 },
 {
  "deadZone": [],
  "id": 4167690192,
  "index": "PBGM121",
  "name": "PBGM121_8in50_BL_MkIX",
  "typeinfo": {
   "nation": "United_Kingdom",
   "species": "Main",
   "type": "Gun"
  }
 },
 {
  "deadZone": [],
  "id": 3715753936,
  "index": "PBGM552",
  "name": "PBGM552_15in42_MK1_RF_LanternFest20",
  "typeinfo": {
   "nation": "United_Kingdom",
   "species": "Main",
   "type": "Gun"
  }
 },
 {
  "deadZone": [],
  "id": 4272547792,
  "index": "PBGM021",
  "name": "PBGM021_6in50_MK_XXI",
  "typeinfo": {
   "nation": "United_Kingdom",
   "species": "Main",
   "type": "Gun"
  }
 },
 {
  "antiAirAuraDistance": -1.0,
  "antiAirAuraStrength": -1.0,
  "id": 3752847312,
  "index": "PBGA517",
  "name": "PBGA517_20mm_Oerlikon_MK_V_Ice",
  "numBarrels": 2,
  "shotDelay": 5.0,
  "typeinfo": {
   "nation": "United_Kingdom",
   "species": "AAircraft",
   "type": "Gun"
  }
 },
 {
  "deadZone": [],
  "id": 3767134160,
  "index": "PBGM503",
  "name": "PBGM503_15in42_MK2_clean",
  "typeinfo": {
   "nation": "United_Kingdom",
   "species": "Main",
   "type": "Gun"
  }
 },
 {
  "deadZone": [],
  "id": 4210681808,
  "index": "PBGM080",
  "name": "PBGM080_4in_45_MkV",
  "typeinfo": {
   "nation": "United_Kingdom",
   "species": "Main",
   "type": "Gun"
  }
 },
 {
  "antiAirAuraDistance": 40.0,
  "antiAirAuraStrength": 0.041,
  "id": 4205832144,
  "index": "PBGA085",
  "name": "PBGA085_13_2mm_2barrels_Breda_MG1",
  "numBarrels": 2,
  "shotDelay": 5.0,
  "typeinfo": {
   "nation": "United_Kingdom",
   "species": "AAircraft",
   "type": "Gun"
  }
 },
 {
  "antiAirAuraDistance": 117.0,
  "antiAirAuraStrength": 0.227,
  "id": 4232046544,
  "index": "PBGA060",
  "name": "PBGA060_40mm_Bofors_Mark_IV_Hazemeyer",
  "numBarrels": 2,
  "shotDelay": 5.0,
  "typeinfo": {
   "nation": "United_Kingdom",
   "species": "AAircraft",
   "type": "Gun"
  }
 },
 {
  "deadZone": [],
  "id": 4233750480,
  "index": "PBGM058",
  "name": "PBGM058_16_5in_45_MkII_Cubic",
  "typeinfo": {
   "nation": "United_Kingdom",
   "species": "Main",
   "type": "Gun"
  }
 },
 {
  "ammoList": [
   "PBPA004_102mm_HE_HE_35lbs"
  ],
  "antiAirAuraDistance": 167.0,
  "antiAirAuraStrength": 0.179,
  "barrelDiameter": 0.102,
  "delim": 0.6,
  "id": 4089898960,
  "idealDistance": 333.333,
  "idealRadius": 20,
  "index": "PBGS195",
  "minRadius": 1.0,
  "name": "PBGS195_4IN45_XIX_M",
  "radiusOnDelim": 0.8,
  "radiusOnMax": 1.0,
  "radiusOnZero": 0.1,
  "rotationSpeed": [
   60.0,
   1.0
  ],
  "shotDelay": 3.0,
  "smokePenalty": 0.0001,
  "typeinfo": {
   "nation": "United_Kingdom",
   "species": "Secondary",
   "type": "Gun"
  },
  "vertSector": [
   -1.0,
   80.0
  ]
 },
 {
  "ammoList": [
   "PBPD001_MkVII"
  ],
  "horizSector": [
   -150.0,
   150.0
  ],
  "id": 4172244944,
  "index": "PBGB117",
  "name": "PBGB117_Depth_Charge_Shelving",
  "numBombs": 6,
  "rotationSpeed": [
   0.0,
   0.0
  ],
  "typeinfo": {
   "nation": "United_Kingdom",
   "species": "DCharge",
   "type": "Gun"
  }
 },
 {
  "antiAirAuraDistance": 40.0,
  "antiAirAuraStrength": 0.021,
  "id": 4208977872,
  "index": "PBGA082",
  "name": "PBGA082_12mm62_HI",
  "numBarrels": 4,
  "shotDelay": 5.0,
  "typeinfo": {
   "nation": "United_Kingdom",
   "species": "AAircraft",
   "type": "Gun"
  }
 },
 {
  "ammoList": [
   "PBPA019_114MM_HE_MK16"
  ],
  "antiAirAuraDistance": 167.0,
  "antiAirAuraStrength": 0.178,
  "barrelDiameter": 0.113,
  "delim": 0.6,
  "id": 4258719696,
  "idealDistance": 333.333,
  "idealRadius": 20,
  "index": "PBGS034",
  "minRadius": 1.0,
  "name": "PBGS034_4_5in45_MK_5",
  "radiusOnDelim": 0.8,
  "radiusOnMax": 1.0,
  "radiusOnZero": 0.1,
  "rotationSpeed": [
   60.0,
   1.0
  ],
  "shotDelay": 3.0,
  "smokePenalty": 0.0001,
  "typeinfo": {
   "nation": "United_Kingdom",
   "species": "Secondary",
   "type": "Gun"
  },
  "vertSector": [
   -1.0,
   80.0
  ]
 },
 {
  "ammoList": [
   "PBPA004_102mm_HE_HE_35lbs"
  ],
  "antiAirAuraDistance": 167.0,
  "antiAirAuraStrength": 0.094,
  "barrelDiameter": 0.102,
  "delim": 0.6,
  "id": 4161202128,
  "idealDistance": 333.333,
  "idealRadius": 20,
  "index": "PBGS127",
  "minRadius": 1.0,
  "name": "PBGS127_4in45_QF_Mk_XIX",
  "radiusOnDelim": 0.8,
  "radiusOnMax": 1.0,
  "radiusOnZero": 0.1,
  "rotationSpeed": [
   60.0,
   1.0
  ],
  "shotDelay": 3.0,
  "smokePenalty": 0.0001,
  "typeinfo": {
   "nation": "United_Kingdom",
   "species": "Secondary",
   "type": "Gun"
  },
  "vertSector": [
   -1.0,
   80.0
  ]
 },
 {
  "deadZone": [],
  "id": 4158253008,
  "index": "PBGM130",
  "name": "PBGM130_127mm_QF_MN2",
  "typeinfo": {
   "nation": "United_Kingdom",
   "species": "Main",
   "type": "Gun"
  }
 },
 {
  "antiAirAuraDistance": 117.0,
  "antiAirAuraStrength": 0.134,
  "id": 4257212368,
  "index": "PBGA036",
  "name": "PBGA036_STAAG_MarkV",
  "numBarrels": 2,
  "shotDelay": 5.0,
  "typeinfo": {
   "nation": "United_Kingdom",
   "species": "AAircraft",
   "type": "Gun"
  }
 },
 {
  "deadZone": [],
  "id": 4169787344,
  "index": "PBGM119",
  "name": "PBGM119_6in50_Quad_Mark_XXIII",
  "typeinfo": {
   "nation": "United_Kingdom",
   "species": "Main",
   "type": "Gun"
  }
 },
 {
  "ammoList": [
   "PBPA004_102mm_HE_HE_35lbs"
  ],
  "antiAirAuraDistance": 117.0,
  "antiAirAuraStrength": 0.028,
  "barrelDiameter": 0.102,
  "delim": 0.6,
  "id": 4280739792,
  "idealDistance": 333.333,
  "idealRadius": 20,
  "index": "PBGS013",
  "minRadius": 1.0,
  "name": "PBGS013_4in_45_MK_V",
  "radiusOnDelim": 0.8,
  "radiusOnMax": 1.0,
  "radiusOnZero": 0.1,
  "rotationSpeed": [
   60.0,
   1.0
  ],
  "shotDelay": 4.0,
  "smokePenalty": 0.0001,
  "typeinfo": {
   "nation": "United_Kingdom",
   "species": "Secondary",
   "type": "Gun"
  },
  "vertSector": [
   -1.0,
   80.0
  ]
 },
 {
  "deadZone": [],
  "id": 3755599824,
  "index": "PBGM514",
  "name": "PBGM514_14in45_BL_MkVII_Twin_Ice",
  "typeinfo": {
   "nation": "United_Kingdom",
   "species": "Main",
   "type": "Gun"
  }
 },
 {
  "antiAirAuraDistance": 133.0,
  "antiAirAuraStrength": 0.394,
  "id": 4262455248,
  "index": "PBGA031",
  "name": "PBGA031_3in70_Mk6",
  "numBarrels": 2,
  "shotDelay": 5.0,
  "typeinfo": {
   "nation": "United_Kingdom",
   "species": "AAircraft",
   "type": "Gun"
  }
 },
 {
  "antiAirAuraDistance": 83.0,
  "antiAirAuraStrength": 0.198,
  "id": 4218415056,
  "index": "PBGA073",
  "name": "PBGA073_2_pdr_MkVIII_8barrel",
  "numBarrels": 8,
  "shotDelay": 5.0,
  "typeinfo": {
   "nation": "United_Kingdom",
   "species": "AAircraft",
   "type": "Gun"
  }
 },
 {
  "ammoList": [
   "PBPD004_200KG"
  ],
  "horizSector": [
   -150.0,
   150.0
  ],
  "id": 4181682128,
  "index": "PBGB108",
  "name": "PBGB108_Squid",
  "numBombs": 3,
  "rotationSpeed": [
   0.0,
   0.0
  ],
  "typeinfo": {
   "nation": "United_Kingdom",
   "species": "DCharge",
   "type": "Gun"
  }
 },
 {
  "ammoList": [
   "PBPD001_MkVII"
  ],
  "horizSector": [
   -150.0,
   150.0
  ],
  "id": 4177487824,
  "index": "PBGB112",
  "name": "PBGB112_Depth_Charge_Roller_Track",
  "numBombs": 3,
  "rotationSpeed": [
   0.0,
   0.0
  ],
  "typeinfo": {
   "nation": "United_Kingdom",
   "species": "DCharge",
   "type": "Gun"
  }
 },
 {
  "deadZone": [],
  "id": 4184467408,
  "index": "PBGM105",
  "name": "PBGM105_8in50_BL_Mk8",
  "typeinfo": {
   "nation": "United_Kingdom",
   "species": "Main",
   "type": "Gun"
  }
 },
 {
  "ammoList": [
   "PBPD001_MkVII"
  ],
  "horizSector": [
   -150.0,
   150.0
  ],
  "id": 4179584976,
  "index": "PBGB110",
  "name": "PBGB110_Depth_Charge_Thrower",
  "numBombs": 1,
  "rotationSpeed": [
   0.0,
   0.0
  ],
  "typeinfo": {
   "nation": "United_Kingdom",
   "species": "DCharge",
   "type": "Gun"
  }
 },
 {
  "antiAirAuraDistance": -1.0,
  "antiAirAuraStrength": -1.0,
  "id": 3750750160,
  "index": "PBGA519",
  "name": "PBGA519_2_pdr_MkVII_Quad_Ice",
  "numBarrels": 2,
  "shotDelay": 5.0,
  "typeinfo": {
   "nation": "United_Kingdom",
   "species": "AAircraft",
   "type": "Gun"
  }
 },
 {
  "deadZone": [],
  "id": 3766085584,
  "index": "PBGM504",
  "name": "PBGM504_15in42_MK2_B_clean",
  "typeinfo": {
   "nation": "United_Kingdom",
   "species": "Main",
   "type": "Gun"
  }
 },
 {
  "ammoList": [
   ""
  ],
  "barrelDiameter": 0.533,
  "id": 4199966672,
  "index": "PBGT090",
  "name": "PBGT090_21in_5tube_Torpedo_Tube",
  "numBarrels": 5,
  "rotationSpeed": [
   25.0,
   25.0
  ],
  "shotDelay": 106.0,
  "torpedoAngles": [
   3.6,
   4.8
  ],
  "typeinfo": {
   "nation": "United_Kingdom",
   "species": "Torpedo",
   "type": "Gun"
  }
 },
 {
  "antiAirAuraDistance": 83.0,
  "antiAirAuraStrength": 0.057,
  "id": 4192200656,
  "index": "PBGA098",
  "name": "PBGA098_40mm_2pdr_QF_MKII_PomPom",
  "numBarrels": 1,
  "shotDelay": 5.0,
  "typeinfo": {
   "nation": "United_Kingdom",
   "species": "AAircraft",
   "type": "Gun"
  }
 },
 {
  "antiAirAuraDistance": 117.0,
  "antiAirAuraStrength": 0.123,
  "id": 4193249232,
  "index": "PBGA097",
  "name": "PBGA097_40mm_Bofors_Mk1",
  "numBarrels": 2,
  "shotDelay": 5.0,
  "typeinfo": {
   "nation": "United_Kingdom",
   "species": "AAircraft",
   "type": "Gun"
  }
 },
 {
  "antiAirAuraDistance": 40.0,
  "antiAirAuraStrength": 0.038,
  "id": 4265600976,
  "index": "PBGA028",
  "name": "PBGA028_Browning_M2_Mod2",
  "numBarrels": 1,
  "shotDelay": 5.0,
  "typeinfo": {
   "nation": "United_Kingdom",
   "species": "AAircraft",
   "type": "Gun"
  }
 },
 {
  "deadZone": [],
  "id": 4229556176,
  "index": "PBGM062",
  "name": "PBGM062_18in_45",
  "typeinfo": {
   "nation": "United_Kingdom",
   "species": "Main",
   "type": "Gun"
  }
 },
 {
  "deadZone": [],
  "id": 4209633232,
  "index": "PBGM081",
  "name": "PBGM081_15in_45_MkII",
  "typeinfo": {
   "nation": "United_Kingdom",
   "species": "Main",
   "type": "Gun"
  }
 },
 {
  "deadZone": [],
  "id": 4187613136,
  "index": "PBGM102",
  "name": "PBGM102_4_5in45_MK_5",
  "typeinfo": {
   "nation": "United_Kingdom",
   "species": "Main",
   "type": "Gun"
  }
 },
 {
  "deadZone": [],
  "id": 4148815824,
  "index": "PBGM139",
  "name": "PBGM139_5_25in_50_QF_MkI_MkII",
  "typeinfo": {
   "nation": "United_Kingdom",
   "species": "Main",
   "type": "Gun"
  }
 },
 {
  "antiAirAuraDistance": 50.0,
  "antiAirAuraStrength": 0.1,
  "id": 4243580880,
  "index": "PBGA049",
  "name": "PBGA049_UP_launcher",
  "numBarrels": 20,
  "shotDelay": 5.0,
  "typeinfo": {
   "nation": "United_Kingdom",
   "species": "AAircraft",
   "type": "Gun"
  }
 },
 {
  "deadZone": [],
  "id": 4232701904,
  "index": "PBGM059",
  "name": "PBGM059_16_5in_45_MkII_Rounded",
  "typeinfo": {
   "nation": "United_Kingdom",
   "species": "Main",
   "type": "Gun"
  }
 },
 {
  "deadZone": [],
  "id": 3768182736,
  "index": "PBGM502",
  "name": "PBGM502_15in42_MK2_B_Nolan",
  "typeinfo": {
   "nation": "United_Kingdom",
   "species": "Main",
   "type": "Gun"
  }
 },
 {
  "ammoList": [
   "PBPD001_MkVII"
  ],
  "horizSector": [
   -150.0,
   150.0
  ],
  "id": 4175390672,
  "index": "PBGB114",
  "name": "PBGB114_Depth_Charge_Shelving",
  "numBombs": 5,
  "rotationSpeed": [
   0.0,
   0.0
  ],
  "typeinfo": {
   "nation": "United_Kingdom",
   "species": "DCharge",
   "type": "Gun"
  }
 },
 {
  "antiAirAuraDistance": 67.0,
  "antiAirAuraStrength": 0.056,
  "id": 4248823760,
  "index": "PBGA044",
  "name": "PBGA044_40mm_Vickers",
  "numBarrels": 1,
  "shotDelay": 5.0,
  "typeinfo": {
   "nation": "United_Kingdom",
   "species": "AAircraft",
   "type": "Gun"
  }
 },
 {
  "antiAirAuraDistance": 83.0,
  "antiAirAuraStrength": 0.14,
  "id": 4292863952,
  "index": "PBGA002",
  "name": "PBGA002_2_pdr_MkVII_Quad",
  "numBarrels": 4,
  "shotDelay": 5.0,
  "typeinfo": {
   "nation": "United_Kingdom",
   "species": "AAircraft",
   "type": "Gun"
  }
 },
 {
  "ammoList": [
   "PBPD001_MkVII"
  ],
  "horizSector": [
   -150.0,
   150.0
  ],
  "id": 4167002064,
  "index": "PBGB122",
  "name": "PBGB122_Icarus_Depth_Charge_fake",
  "numBombs": 3,
  "rotationSpeed": [
   0.0,
   0.0
  ],
  "typeinfo": {
   "nation": "United_Kingdom",
   "species": "DCharge",
   "type": "Gun"
  }
 },
 {
  "ammoList": [
   "PBPD001_MkVII"
  ],
  "horizSector": [
   -150.0,
   150.0
  ],
  "id": 4174342096,
  "index": "PBGB115",
  "name": "PBGB115_Depth_Charge_Roller_Track",
  "numBombs": 6,
  "rotationSpeed": [
   0.0,
   0.0
  ],
  "typeinfo": {
   "nation": "United_Kingdom",
   "species": "DCharge",
   "type": "Gun"
  }
 },
 {
  "antiAirAuraDistance": -1.0,
  "antiAirAuraStrength": -1.0,
  "id": 3751798736,
  "index": "PBGA518",
  "name": "PBGA518_40mm_Bofors_Mk2_Ice",
  "numBarrels": 2,
  "shotDelay": 5.0,
  "typeinfo": {
   "nation": "United_Kingdom",
   "species": "AAircraft",
   "type": "Gun"
  }
 },
 {
  "ammoList": [
   "PBPD001_MkVII"
  ],
  "horizSector": [
   -150.0,
   150.0
  ],
  "id": 4171196368,
  "index": "PBGB118",
  "name": "PBGB118_Depth_Charge_Shelving",
  "numBombs": 3,
  "rotationSpeed": [
   0.0,
   0.0
  ],
  "typeinfo": {
   "nation": "United_Kingdom",
   "species": "DCharge",
   "type": "Gun"
  }
 },
 {
  "deadZone": [],
  "id": 4255770576,
  "index": "PBGM037",
  "name": "PBGM037_6in45_MK_XII",
  "typeinfo": {
   "nation": "United_Kingdom",
   "species": "Main",
   "type": "Gun"
  }
 },
 {
  "deadZone": [],
  "id": 4212778960,
  "index": "PBGM078",
  "name": "PBGM078_16_45_MkII_Rounded",
  "typeinfo": {
   "nation": "United_Kingdom",
   "species": "Main",
   "type": "Gun"
  }
 },
 {
  "ammoList": [
   "PBPA003_152mm_HE_HE4crh"
  ],
  "antiAirAuraDistance": 0.0,
  "antiAirAuraStrength": 0.0,
  "barrelDiameter": 0.152,
  "delim": 0.6,
  "id": 4282836944,
  "idealDistance": 333.333,
  "idealRadius": 12.0,
  "index": "PBGS011",
  "minRadius": 1.0,
  "name": "PBGS011_152mm50_Type41",
  "radiusOnDelim": 0.8,
  "radiusOnMax": 1.0,
  "radiusOnZero": 0.1,
  "rotationSpeed": [
   60.0,
   1.0
  ],
  "shotDelay": 8.6,
  "smokePenalty": 0.0001,
  "typeinfo": {
   "nation": "United_Kingdom",
   "species": "Secondary",
   "type": "Gun"
  },
  "vertSector": [
   -1.0,
   15.0
  ]
 },
 {
  "antiAirAuraDistance": 117.0,
  "antiAirAuraStrength": 0.087,
  "id": 4271892432,
  "index": "PBGA022",
  "name": "PBGA022_40mm_Bofors_MkV",
  "numBarrels": 1,
  "shotDelay": 5.0,
  "typeinfo": {
   "nation": "United_Kingdom",
   "species": "AAircraft",
   "type": "Gun"
  }
 },
 {
  "ammoList": [
   "PBPT010_533_MKIXM"
  ],
  "barrelDiameter": 0.533,
  "id": 4194723792,
  "index": "PBGT095",
  "name": "PBGT095_21in_5tube_Torpedo_Tube",
  "numBarrels": 5,
  "rotationSpeed": [
   25.0,
   25.0
  ],
  "shotDelay": 96.0,
  "torpedoAngles": [
   2.4,
   6.0
  ],
  "typeinfo": {
   "nation": "United_Kingdom",
   "species": "Torpedo",
   "type": "Gun"
  }
 },
 {
  "antiAirAuraDistance": -1.0,
  "antiAirAuraStrength": -1.0,
  "id": 3247433680,
  "index": "PBGA999",
  "name": "PBGA999_UP_launcher_Nolan",
  "numBarrels": 2,
  "shotDelay": 5.0,
  "typeinfo": {
   "nation": "United_Kingdom",
   "species": "AAircraft",
   "type": "Gun"
  }
 },
 {
  "antiAirAuraDistance": 67.0,
  "antiAirAuraStrength": 0.036,
  "id": 4287621072,
  "index": "PBGA007",
  "name": "PBGA007_20mm_Oerlikon_MK4",
  "numBarrels": 1.0,
  "shotDelay": 5.0,
  "typeinfo": {
   "nation": "United_Kingdom",
   "species": "AAircraft",
   "type": "Gun"
  }
 },
 {
  "deadZone": [],
  "id": 4157204432,
  "index": "PBGM131",
  "name": "PBGM131_12in45_MK13",
  "typeinfo": {
   "nation": "United_Kingdom",
   "species": "Main",
   "type": "Gun"
  }
 },
 {
  "deadZone": [],
  "id": 3716802512,
  "index": "PBGM551",
  "name": "PBGM551_15in42_MK1_LanternFest20",
  "typeinfo": {
   "nation": "United_Kingdom",
   "species": "Main",
   "type": "Gun"
  }
 },
 {
  "ammoList": [
   "PBPT008_533_MKIX2"
  ],
  "barrelDiameter": 0.533,
  "id": 4270221264,
  "index": "PBGT023",
  "name": "PBGT023_21in_3tube_TR_Mk_IV_R",
  "numBarrels": 3,
  "rotationSpeed": [
   25.0,
   25.0
  ],
  "shotDelay": 72.0,
  "torpedoAngles": [
   2.4,
   3.6
  ],
  "typeinfo": {
   "nation": "United_Kingdom",
   "species": "Torpedo",
   "type": "Gun"
  }
 },
 {
  "antiAirAuraDistance": 100.0,
  "antiAirAuraStrength": 0.021,
  "id": 4250920912,
  "index": "PBGA042",
  "name": "PBGA042_3in_HA_12PDR",
  "numBarrels": 1,
  "shotDelay": 5.0,
  "typeinfo": {
   "nation": "United_Kingdom",
   "species": "AAircraft",
   "type": "Gun"
  }
 },
 {
  "deadZone": [],
  "id": 4085901264,
  "index": "PBGM199",
  "name": "PBGM199_6IN45_DANAE_EM",
  "typeinfo": {
   "nation": "United_Kingdom",
   "species": "Main",
   "type": "Gun"
  }
 },
 {
  "deadZone": [],
  "id": 4211730384,
  "index": "PBGM079",
  "name": "PBGM079_120mm_45_QF_CP_MkXIX_Twin",
  "typeinfo": {
   "nation": "United_Kingdom",
   "species": "Main",
   "type": "Gun"
  }
 },
 {
  "ammoList": [
   "PBPA041_134MM_MI_HE"
  ],
  "antiAirAuraDistance": 173.0,
  "antiAirAuraStrength": 0.085,
  "barrelDiameter": 0.133,
  "delim": 0.6,
  "id": 4226213840,
  "idealDistance": 333.333,
  "idealRadius": 20,
  "index": "PBGS065",
  "minRadius": 1.0,
  "name": "PBGS065_5_25in_50_RP10_Mk_Istar",
  "radiusOnDelim": 0.8,
  "radiusOnMax": 1.0,
  "radiusOnZero": 0.1,
  "rotationSpeed": [
   60.0,
   1.0
  ],
  "shotDelay": 6.67,
  "smokePenalty": 0.0001,
  "typeinfo": {
   "nation": "United_Kingdom",
   "species": "Secondary",
   "type": "Gun"
  },
  "vertSector": [
   -1.0,
   70.0
  ]
 },
 {
  "antiAirAuraDistance": 83.0,
  "antiAirAuraStrength": 0.057,
  "id": 4224706512,
  "index": "PBGA067",
  "name": "PBGA067_2pdr_QF_MKII_PomPom",
  "numBarrels": 1,
  "shotDelay": 5.0,
  "typeinfo": {
   "nation": "United_Kingdom",
   "species": "AAircraft",
   "type": "Gun"
  }
 },
 {
  "antiAirAuraDistance": 117.0,
  "antiAirAuraStrength": 0.123,
  "id": 4268746704,
  "index": "PBGA025",
  "name": "PBGA025_40mm_Bofors_Twin",
  "numBarrels": 2,
  "shotDelay": 5.0,
  "typeinfo": {
   "nation": "United_Kingdom",
   "species": "AAircraft",
   "type": "Gun"
  }
 },
 {
  "deadZone": [],
  "id": 4235847632,
  "index": "PBGM056",
  "name": "PBGM056_14in45_BL_MkVII_Quadro",
  "typeinfo": {
   "nation": "United_Kingdom",
   "species": "Main",
   "type": "Gun"
  }
 },
 {
  "deadZone": [],
  "id": 4225361872,
  "index": "PBGM066",
  "name": "PBGM066_16in45_BL_MkI",
  "typeinfo": {
   "nation": "United_Kingdom",
   "species": "Main",
   "type": "Gun"
  }
 },
 {
  "deadZone": [],
  "id": 4215924688,
  "index": "PBGM075",
  "name": "PBGM075_120mm_45_QF_MkIX",
  "typeinfo": {
   "nation": "United_Kingdom",
   "species": "Main",
   "type": "Gun"
  }
 },
 {
  "antiAirAuraDistance": 83.0,
  "antiAirAuraStrength": 0.129,
  "id": 4219463632,
  "index": "PBGA072",
  "name": "PBGA072_2_pdr_MkVII_Quad",
  "numBarrels": 4,
  "shotDelay": 5.0,
  "typeinfo": {
   "nation": "United_Kingdom",
   "species": "AAircraft",
   "type": "Gun"
  }
 },
 {
  "deadZone": [],
  "id": 3757696976,
  "index": "PBGM512",
  "name": "PBGM512_14in45_BL_MkVII_Quadro_Ice",
  "typeinfo": {
   "nation": "United_Kingdom",
   "species": "Main",
   "type": "Gun"
  }
 },
 {
  "antiAirAuraDistance": 117.0,
  "antiAirAuraStrength": 0.234,
  "id": 4091537360,
  "index": "PBGA194",
  "name": "PBGA194_40MM_BOFORS_5_RP50",
  "numBarrels": 2,
  "shotDelay": 5.0,
  "typeinfo": {
   "nation": "United_Kingdom",
   "species": "AAircraft",
   "type": "Gun"
  }
 },
 {
  "antiAirAuraDistance": 67.0,
  "antiAirAuraStrength": 0.036,
  "id": 4152354768,
  "index": "PBGA136",
  "name": "PBGA136_20mm_Oerlikon_MK4",
  "numBarrels": 1,
  "shotDelay": 5.0,
  "typeinfo": {
   "nation": "United_Kingdom",
   "species": "AAircraft",
   "type": "Gun"
  }
 },
 {
  "ammoList": [
   "PBPA104_102MM_HE_31LBS"
  ],
  "antiAirAuraDistance": 0.0,
  "antiAirAuraStrength": 0.0,
  "barrelDiameter": 0.102,
  "delim": 0.6,
  "id": 4152813520,
  "idealDistance": 333.333,
  "idealRadius": 20,
  "index": "PBGS135",
  "minRadius": 1.0,
  "name": "PBGS135_4in_102_Mk_IX_TI_Mk_1",
  "radiusOnDelim": 0.8,
  "radiusOnMax": 1.0,
  "radiusOnZero": 0.1,
  "rotationSpeed": [
   60.0,
   1.0
  ],
  "shotDelay": 6.0,
  "smokePenalty": 0.0001,
  "typeinfo": {
   "nation": "United_Kingdom",
   "species": "Secondary",
   "type": "Gun"
  },
  "vertSector": [
   -1.0,
   28.0
  ]
 },
 {
  "ammoList": [
   "PBPT006_533_MKVII"
  ],
  "barrelDiameter": 0.533,
  "id": 4241909712,
  "index": "PBGT050",
  "name": "PBGT050_21in_4tube_QR_Mk_VII_R",
  "numBarrels": 4,
  "rotationSpeed": [
   25.0,
   25.0
  ],
  "shotDelay": 106.0,
  "torpedoAngles": [
   4.8,
   16.0
  ],
  "typeinfo": {
   "nation": "United_Kingdom",
   "species": "Torpedo",
   "type": "Gun"
  }
 },
 {
  "ammoList": [
   "PBPA073_76MM_HE_MK27M1"
  ],
  "antiAirAuraDistance": 0.0,
  "antiAirAuraStrength": 0.0,
  "barrelDiameter": 0.076,
  "delim": 0.6,
  "id": 4186367952,
  "idealDistance": 333.333,
  "idealRadius": 20,
  "index": "PBGS103",
  "minRadius": 1.0,
  "name": "PBGS103_3in50_QF_12pdr_18cwt",
  "radiusOnDelim": 0.8,
  "radiusOnMax": 1.0,
  "radiusOnZero": 0.1,
  "rotationSpeed": [
   60.0,
   1.0
  ],
  "shotDelay": 5.0,
  "smokePenalty": 0.0001,
  "typeinfo": {
   "nation": "United_Kingdom",
   "species": "Secondary",
   "type": "Gun"
  },
  "vertSector": [
   -3.0,
   15.0
  ]
 },
 {
  "ammoList": [
   "PBPD004_200KG"
  ],
  "horizSector": [
   -150.0,
   150.0
  ],
  "id": 4180633552,
  "index": "PBGB109",
  "name": "PBGB109_Limbo",
  "numBombs": 3,
  "rotationSpeed": [
   0.0,
   0.0
  ],
  "typeinfo": {
   "nation": "United_Kingdom",
   "species": "DCharge",
   "type": "Gun"
  }
 },
 {
  "ammoList": [
   "PBPA030_102MM_MVII_HE"
  ],
  "antiAirAuraDistance": 0.0,
  "antiAirAuraStrength": 0.0,
  "barrelDiameter": 0.102,
  "delim": 0.6,
  "id": 4237748176,
  "idealDistance": 333.333,
  "idealRadius": 20,
  "index": "PBGS054",
  "minRadius": 1.0,
  "name": "PBGS054_4in50_BL_MKVII",
  "radiusOnDelim": 0.8,
  "radiusOnMax": 1.0,
  "radiusOnZero": 0.1,
  "rotationSpeed": [
   60.0,
   1.0
  ],
  "shotDelay": 7.5,
  "smokePenalty": 0.0001,
  "typeinfo": {
   "nation": "United_Kingdom",
   "species": "Secondary",
   "type": "Gun"
  },
  "vertSector": [
   -1.0,
   15.0
  ]
 },
 {
  "deadZone": [],
  "id": 4165593040,
  "index": "PBGM123",
  "name": "PBGM123_7_5in45_BL_MkVI",
  "typeinfo": {
   "nation": "United_Kingdom",
   "species": "Main",
   "type": "Gun"
  }
 },
 {
  "deadZone": [],
  "id": 4204390352,
  "index": "PBGM086",
  "name": "PBGM086_4_7in_50QF_MKXI",
  "typeinfo": {
   "nation": "United_Kingdom",
   "species": "Main",
   "type": "Gun"
  }
 },
 {
  "deadZone": [],
  "id": 3769231312,
  "index": "PBGM501",
  "name": "PBGM501_15in42_MK2_Nolan",
  "typeinfo": {
   "nation": "United_Kingdom",
   "species": "Main",
   "type": "Gun"
  }
 },
 {
  "ammoList": [
   "PBPT004_533_MKII"
  ],
  "barrelDiameter": 0.533,
  "id": 4254492624,
  "index": "PBGT038",
  "name": "PBGT038_21in_Triple_Torpedo_Tube",
  "numBarrels": 3,
  "rotationSpeed": [
   25.0,
   25.0
  ],
  "shotDelay": 62.0,
  "torpedoAngles": [
   2.4,
   3.6
  ],
  "typeinfo": {
   "nation": "United_Kingdom",
   "species": "Torpedo",
   "type": "Gun"
  }
 },
 {
  "ammoList": [
   "PBPT006_533_MKVII"
  ],
  "barrelDiameter": 0.533,
  "id": 4240861136,
  "index": "PBGT051",
  "name": "PBGT051_21in_4tube_QR_Mk_VII_L",
  "numBarrels": 4,
  "rotationSpeed": [
   25.0,
   25.0
  ],
  "shotDelay": 106.0,
  "torpedoAngles": [
   4.8,
   16.0
  ],
  "typeinfo": {
   "nation": "United_Kingdom",
   "species": "Torpedo",
   "type": "Gun"
  }
 },
 {
  "deadZone": [],
  "id": 4203341776,
  "index": "PBGM087",
  "name": "PBGM087_4_5in_45_Mk4_2barrels",
  "typeinfo": {
   "nation": "United_Kingdom",
   "species": "Main",
   "type": "Gun"
  }
 },
 {
  "antiAirAuraDistance": 33.0,
  "antiAirAuraStrength": 0.017,
  "id": 4247775184,
  "index": "PBGA045",
  "name": "PBGA045_MachineGunMaxim_7_62",
  "numBarrels": 1,
  "shotDelay": 5.0,
  "typeinfo": {
   "nation": "United_Kingdom",
   "species": "AAircraft",
   "type": "Gun"
  }
 },
 {
  "deadZone": [],
  "id": 4238993360,
  "index": "PBGM053",
  "name": "PBGM053_4in45_QF_Mk_XIX",
  "typeinfo": {
   "nation": "United_Kingdom",
   "species": "Main",
   "type": "Gun"
  }
 },
 {
  "ammoList": [
   "PBPA019_114MM_HE_MK16"
  ],
  "antiAirAuraDistance": 167.0,
  "antiAirAuraStrength": 0.149,
  "barrelDiameter": 0.113,
  "delim": 0.6,
  "id": 4150716368,
  "idealDistance": 333.333,
  "idealRadius": 20,
  "index": "PBGS137",
  "minRadius": 1.0,
  "name": "PBGS137_4_5in_45_MK3_BD_MK2",
  "radiusOnDelim": 0.8,
  "radiusOnMax": 1.0,
  "radiusOnZero": 0.1,
  "rotationSpeed": [
   60.0,
   1.0
  ],
  "shotDelay": 5.0,
  "smokePenalty": 0.0001,
  "typeinfo": {
   "nation": "United_Kingdom",
   "species": "Secondary",
   "type": "Gun"
  },
  "vertSector": [
   -1.0,
   80.0
  ]
 },
 {
  "ammoList": [
   "PBPT004_533_MKII"
  ],
  "barrelDiameter": 0.533,
  "id": 4251346896,
  "index": "PBGT041",
  "name": "PBGT041_21in_Torpedo_Tubes_Twin_R",
  "numBarrels": 2,
  "rotationSpeed": [
   25.0,
   25.0
  ],
  "shotDelay": 41.0,
  "torpedoAngles": [
   2.2,
   2.4
  ],
  "typeinfo": {
   "nation": "United_Kingdom",
   "species": "Torpedo",
   "type": "Gun"
  }
 },
 {
  "ammoList": [
   "PBPA037_120MM_MXII_HE"
  ],
  "antiAirAuraDistance": 150.0,
  "antiAirAuraStrength": 0.06,
  "barrelDiameter": 0.12,
  "delim": 0.6,
  "id": 4227262416,
  "idealDistance": 333.333,
  "idealRadius": 20,
  "index": "PBGS064",
  "minRadius": 1.0,
  "name": "PBGS064_4_7in40_QF_MkVIII",
  "radiusOnDelim": 0.8,
  "radiusOnMax": 1.0,
  "radiusOnZero": 0.1,
  "rotationSpeed": [
   60.0,
   1.0
  ],
  "shotDelay": 5.0,
  "smokePenalty": 0.0001,
  "typeinfo": {
   "nation": "United_Kingdom",
   "species": "Secondary",
   "type": "Gun"
  },
  "vertSector": [
   -1.0,
   75.0
  ]
 },
 {
  "deadZone": [],
  "id": 4234799056,
  "index": "PBGM057",
  "name": "PBGM057_14in45_BL_MkVII_Twin",
  "typeinfo": {
   "nation": "United_Kingdom",
   "species": "Main",
   "type": "Gun"
  }
 },
 {
  "ammoList": [
   "PBPA019_114MM_HE_MK16"
  ],
  "antiAirAuraDistance": 167.0,
  "antiAirAuraStrength": 0.089,
  "barrelDiameter": 0.113,
  "delim": 0.6,
  "id": 4193707984,
  "idealDistance": 333.333,
  "idealRadius": 20,
  "index": "PBGS096",
  "minRadius": 1.0,
  "name": "PBGS096_4_5in45_Mark_III_UD",
  "radiusOnDelim": 0.8,
  "radiusOnMax": 1.0,
  "radiusOnZero": 0.1,
  "rotationSpeed": [
   60.0,
   1.0
  ],
  "shotDelay": 5.0,
  "smokePenalty": 0.0001,
  "typeinfo": {
   "nation": "United_Kingdom",
   "species": "Secondary",
   "type": "Gun"
  },
  "vertSector": [
   -1.0,
   80.0
  ]
 },
 {
  "antiAirAuraDistance": 67.0,
  "antiAirAuraStrength": 0.034,
  "id": 4207929296,
  "index": "PBGA083",
  "name": "PBGA083_Breda_20mm_65",
  "numBarrels": 1,
  "shotDelay": 5.0,
  "typeinfo": {
   "nation": "United_Kingdom",
   "species": "AAircraft",
   "type": "Gun"
  }
 },
 {
  "ammoList": [
   "PBPT006_533_MKVII"
  ],
  "barrelDiameter": 0.533,
  "id": 4214646736,
  "index": "PBGT076",
  "name": "PBGT076_21in_Quad_Torpedo_Tube",
  "numBarrels": 4,
  "rotationSpeed": [
   25.0,
   25.0
  ],
  "shotDelay": 120.0,
  "torpedoAngles": [
   3.6,
   4.8
  ],
  "typeinfo": {
   "nation": "United_Kingdom",
   "species": "Torpedo",
   "type": "Gun"
  }
 },
 {
  "antiAirAuraDistance": 100.0,
  "antiAirAuraStrength": 0.021,
  "id": 4261406672,
  "index": "PBGA032",
  "name": "PBGA032_12pdr_12cwt_Mk9",
  "numBarrels": 1,
  "shotDelay": 5.0,
  "typeinfo": {
   "nation": "United_Kingdom",
   "species": "AAircraft",
   "type": "Gun"
  }
 },
 {
  "ammoList": [
   "PCPD010_Big"
  ],
  "horizSector": [
   -150.0,
   150.0
  ],
  "id": 3762251728,
  "index": "PBGB508",
  "name": "PBGB508_Depth_Charge_Thrower_Space",
  "numBombs": 0,
  "rotationSpeed": [
   0.0,
   0.0
  ],
  "typeinfo": {
   "nation": "United_Kingdom",
   "species": "DCharge",
   "type": "Gun"
  }
 },
 {
  "antiAirAuraDistance": -1.0,
  "antiAirAuraStrength": -1.0,
  "id": 3248482256,
  "index": "PBGA998",
  "name": "PBGA998_UP_launcher_clean",
  "numBarrels": 2,
  "shotDelay": 5.0,
  "typeinfo": {
   "nation": "United_Kingdom",
   "species": "AAircraft",
   "type": "Gun"
  }
 },
 {
  "deadZone": [],
  "id": 4168738768,
  "index": "PBGM120",
  "name": "PBGM120_20in45_Mark_1_twin",
  "typeinfo": {
   "nation": "United_Kingdom",
   "species": "Main",
   "type": "Gun"
  }
 },
 {
  "antiAirAuraDistance": 83.0,
  "antiAirAuraStrength": 0.129,
  "id": 4202686416,
  "index": "PBGA088",
  "name": "PBGA088_2_pdr_MkVII_Quad",
  "numBarrels": 4,
  "shotDelay": 5.0,
  "typeinfo": {
   "nation": "United_Kingdom",
   "species": "AAircraft",
   "type": "Gun"
  }
 },
 {
  "deadZone": [],
  "id": 4240041936,
  "index": "PBGM052",
  "name": "PBGM052_15in42_MK2_B",
  "typeinfo": {
   "nation": "United_Kingdom",
   "species": "Main",
   "type": "Gun"
  }
 },
 {
  "deadZone": [],
  "id": 4162447312,
  "index": "PBGM126",
  "name": "PBGM126_8in50_MK1_RF",
  "typeinfo": {
   "nation": "United_Kingdom",
   "species": "Main",
   "type": "Gun"
  }
 },
 {
  "deadZone": [],
  "id": 4252624848,
  "index": "PBGM040",
  "name": "PBGM040_234mm50_Mk_XII_Triple",
  "typeinfo": {
   "nation": "United_Kingdom",
   "species": "Main",
   "type": "Gun"
  }
 },
 {
  "ammoList": [
   "PBPT004_533_MKII"
  ],
  "barrelDiameter": 0.533,
  "id": 4195772368,
  "index": "PBGT094",
  "name": "PBGT094_21in_Torpedo_Tubes_Twin",
  "numBarrels": 2,
  "rotationSpeed": [
   25.0,
   25.0
  ],
  "shotDelay": 70.0,
  "torpedoAngles": [
   2.2,
   2.4
  ],
  "typeinfo": {
   "nation": "United_Kingdom",
   "species": "Torpedo",
   "type": "Gun"
  }
 },
 {
  "deadZone": [],
  "id": 4154058704,
  "index": "PBGM134",
  "name": "PBGM134_9_2in_Mark_X_Quadruple",
  "typeinfo": {
   "nation": "United_Kingdom",
   "species": "Main",
   "type": "Gun"
  }
 },
 {
  "ammoList": [
   "PCPA001_Shell"
  ],
  "antiAirAuraDistance": -1.0,
  "antiAirAuraStrength": -1.0,
  "barrelDiameter": 20,
  "delim": 0.6,
  "id": 3764840400,
  "idealDistance": 333.333,
  "idealRadius": 20,
  "index": "PBGS505",
  "minRadius": 1.0,
  "name": "PBGS505_4in45_QF_Mk_XIX_Nolan",
  "radiusOnDelim": 0.8,
  "radiusOnMax": 1.0,
  "radiusOnZero": 0.1,
  "rotationSpeed": [
   60.0,
   1.0
  ],
  "shotDelay": 5.0,
  "smokePenalty": 0.0001,
  "typeinfo": {
   "nation": "United_Kingdom",
   "species": "Secondary",
   "type": "Gun"
  },
  "vertSector": [
   -1.0,
   90.0
  ]
 },
 {
  "ammoList": [
   "PCPA001_Shell"
  ],
  "antiAirAuraDistance": -1.0,
  "antiAirAuraStrength": -1.0,
  "barrelDiameter": 20,
  "delim": 0.6,
  "id": 3714508752,
  "idealDistance": 333.333,
  "idealRadius": 20,
  "index": "PBGS553",
  "minRadius": 1.0,
  "name": "PBGS553_4in45_QF_Mk_XIX_LanternFest20",
  "radiusOnDelim": 0.8,
  "radiusOnMax": 1.0,
  "radiusOnZero": 0.1,
  "rotationSpeed": [
   60.0,
   1.0
  ],
  "shotDelay": 5.0,
  "smokePenalty": 0.0001,
  "typeinfo": {
   "nation": "United_Kingdom",
   "species": "Secondary",
   "type": "Gun"
  },
  "vertSector": [
   -1.0,
   90.0
  ]
 },
 {
  "antiAirAuraDistance": 83.0,
  "antiAirAuraStrength": 0.198,
  "id": 4286572496,
  "index": "PBGA008",
  "name": "PBGA008_2_pdr_MkVIII_8barrel",
  "numBarrels": 8,
  "shotDelay": 5.0,
  "typeinfo": {
   "nation": "United_Kingdom",
   "species": "AAircraft",
   "type": "Gun"
  }
 },
 {
  "antiAirAuraDistance": 117.0,
  "antiAirAuraStrength": 0.087,
  "id": 4230997968,
  "index": "PBGA061",
  "name": "PBGA061_40mm_Bofors_Mark_VII_single",
  "numBarrels": 1,
  "shotDelay": 5.0,
  "typeinfo": {
   "nation": "United_Kingdom",
   "species": "AAircraft",
   "type": "Gun"
  }
 },
 {
  "deadZone": [],
  "id": 4183418832,
  "index": "PBGM106",
  "name": "PBGM106_15in42_MK1_RF_Vanguard",
  "typeinfo": {
   "nation": "United_Kingdom",
   "species": "Main",
   "type": "Gun"
  }
 },
 {
  "ammoList": [
   "PBPA030_102MM_MVII_HE"
  ],
  "antiAirAuraDistance": 0.0,
  "antiAirAuraStrength": 0.0,
  "barrelDiameter": 0.102,
  "delim": 0.6,
  "id": 4219922384,
  "idealDistance": 333.333,
  "idealRadius": 20,
  "index": "PBGS071",
  "minRadius": 1.0,
  "name": "PBGS071_4in_50_BL_MKVII",
  "radiusOnDelim": 0.8,
  "radiusOnMax": 1.0,
  "radiusOnZero": 0.1,
  "rotationSpeed": [
   60.0,
   1.0
  ],
  "shotDelay": 7.5,
  "smokePenalty": 0.0001,
  "typeinfo": {
   "nation": "United_Kingdom",
   "species": "Secondary",
   "type": "Gun"
  },
  "vertSector": [
   -1.0,
   15.0
  ]
 },
 {
  "ammoList": [
   "PBPT003_CAMPBELTOWN"
  ],
  "barrelDiameter": 0.533,
  "id": 4262881232,
  "index": "PBGT030",
  "name": "PBGT030_21in_Torpedo_Tubes_Triple",
  "numBarrels": 3,
  "rotationSpeed": [
   25.0,
   25.0
  ],
  "shotDelay": 63.0,
  "torpedoAngles": [
   3.6,
   12.0
  ],
  "typeinfo": {
   "nation": "United_Kingdom",
   "species": "Torpedo",
   "type": "Gun"
  }
 },
 {
  "ammoList": [
   "PCPA001_Shell"
  ],
  "antiAirAuraDistance": -1.0,
  "antiAirAuraStrength": -1.0,
  "barrelDiameter": 20,
  "delim": 0.6,
  "id": 3763791824,
  "idealDistance": 333.333,
  "idealRadius": 20,
  "index": "PBGS506",
  "minRadius": 1.0,
  "name": "PBGS506_4in45_QF_Mk_XIX_clean",
  "radiusOnDelim": 0.8,
  "radiusOnMax": 1.0,
  "radiusOnZero": 0.1,
  "rotationSpeed": [
   60.0,
   1.0
  ],
  "shotDelay": 5.0,
  "smokePenalty": 0.0001,
  "typeinfo": {
   "nation": "United_Kingdom",
   "species": "Secondary",
   "type": "Gun"
  },
  "vertSector": [
   -1.0,
   90.0
  ]
 },
 {
  "deadZone": [],
  "id": 4222216144,
  "index": "PBGM069",
  "name": "PBGM069_12in45_MkX",
  "typeinfo": {
   "nation": "United_Kingdom",
   "species": "Main",
   "type": "Gun"
  }
 },
 {
  "ammoList": [
   "PBPT010_533_MKIXM"
  ],
  "barrelDiameter": 0.533,
  "id": 4289095632,
  "index": "PBGT005",
  "name": "PBGT005_21in_Quad_Torpedo_Tube",
  "numBarrels": 4,
  "rotationSpeed": [
   25.0,
   25.0
  ],
  "shotDelay": 96.0,
  "torpedoAngles": [
   2.4,
   4.8
  ],
  "typeinfo": {
   "nation": "United_Kingdom",
   "species": "Torpedo",
   "type": "Gun"
  }
 },
 {
  "deadZone": [],
  "id": 4228507600,
  "index": "PBGM063",
  "name": "PBGM063_13_5IN_45_Mark_V",
  "typeinfo": {
   "nation": "United_Kingdom",
   "species": "Main",
   "type": "Gun"
  }
 },
 {
  "deadZone": [],
  "id": 4086949840,
  "index": "PBGM198",
  "name": "PBGM198_6IN50_NEPTUNE",
  "typeinfo": {
   "nation": "United_Kingdom",
   "species": "Main",
   "type": "Gun"
  }
 },
 {
  "deadZone": [],
  "id": 4197050320,
  "index": "PBGM093",
  "name": "PBGM093_4_5in_45_Mk4_1barrel",
  "typeinfo": {
   "nation": "United_Kingdom",
   "species": "Main",
   "type": "Gun"
  }
 },
 {
  "ammoList": [
   "PCPA001_Shell"
  ],
  "antiAirAuraDistance": -1.0,
  "antiAirAuraStrength": -1.0,
  "barrelDiameter": 20,
  "delim": 0.6,
  "id": 3713460176,
  "idealDistance": 333.333,
  "idealRadius": 20,
  "index": "PBGS554",
  "minRadius": 1.0,
  "name": "PBGS554_152mm_Type41_LanternFest20",
  "radiusOnDelim": 0.8,
  "radiusOnMax": 1.0,
  "radiusOnZero": 0.1,
  "rotationSpeed": [
   60.0,
   1.0
  ],
  "shotDelay": 5.0,
  "smokePenalty": 0.0001,
  "typeinfo": {
   "nation": "United_Kingdom",
   "species": "Secondary",
   "type": "Gun"
  },
  "vertSector": [
   -1.0,
   90.0
  ]
 },
 {
  "ammoList": [
   "PBPT004_533_MKII"
  ],
  "barrelDiameter": 0.533,
  "id": 4246104016,
  "index": "PBGT046",
  "name": "PBGT046_21in_Torpedo_Tubes_Twin_L",
  "numBarrels": 2,
  "rotationSpeed": [
   25.0,
   25.0
  ],
  "shotDelay": 41.0,
  "torpedoAngles": [
   2.2,
   2.4
  ],
  "typeinfo": {
   "nation": "United_Kingdom",
   "species": "Torpedo",
   "type": "Gun"
  }
 },
 {
  "ammoList": [
   "PBPD001_MkVII"
  ],
  "horizSector": [
   -150.0,
   150.0
  ],
  "id": 4178536400,
  "index": "PBGB111",
  "name": "PBGB111_Depth_Charge_Dumper",
  "numBombs": 1,
  "rotationSpeed": [
   0.0,
   0.0
  ],
  "typeinfo": {
   "nation": "United_Kingdom",
   "species": "DCharge",
   "type": "Gun"
  }
 },
 {
  "ammoList": [
   "PBPD001_MkVII"
  ],
  "horizSector": [
   -150.0,
   150.0
  ],
  "id": 4173293520,
  "index": "PBGB116",
  "name": "PBGB116_Depth_Charge_Shelving",
  "numBombs": 6,
  "rotationSpeed": [
   0.0,
   0.0
  ],
  "typeinfo": {
   "nation": "United_Kingdom",
   "species": "DCharge",
   "type": "Gun"
  }
 },
 {
  "antiAirAuraDistance": 40.0,
  "antiAirAuraStrength": 0.021,
  "id": 4290766800,
  "index": "PBGA004",
  "name": "PBGA004_12mm62_HI",
  "numBarrels": 4,
  "shotDelay": 5.0,
  "typeinfo": {
   "nation": "United_Kingdom",
   "species": "AAircraft",
   "type": "Gun"
  }
 },
 {
  "deadZone": [],
  "id": 4277790672,
  "index": "PBGM016",
  "name": "PBGM016_6in50_MK_XI",
  "typeinfo": {
   "nation": "United_Kingdom",
   "species": "Main",
   "type": "Gun"
  }
 },
 {
  "ammoList": [
   "PBPD002_Depth_Charge"
  ],
  "horizSector": [
   -150.0,
   150.0
  ],
  "id": 4176439248,
  "index": "PBGB113",
  "name": "PBGB113_Depth_Charge_Thornycroft",
  "numBombs": 1,
  "rotationSpeed": [
   0.0,
   0.0
  ],
  "typeinfo": {
   "nation": "United_Kingdom",
   "species": "DCharge",
   "type": "Gun"
  }
 }
]