[
 {
  "angle": 0.0,
  "dist": 0.0,
  "hidePlane": false,
  "id": 4290966736,
  "index": "PZC003",
  "linkedGunAngles": [],
  "linkedGunName": null,
  "linkedRotationSpeedCoeff": 1.0,
  "model": "content/gameplay/panasia/catapult/ZC003_Catapult/ZC003_Catapult.model",
  "name": "PZC003_Catapult",
  "rotateTime": 0.0,
  "typeinfo": {
   "nation": "Pan_Asia",
   "species": null,
   "type": "Catapult"
  }
 },
 {
  "angle": 0.0,
  "dist": 0.0,
  "hidePlane": false,
  "id": 4292015312,
  "index": "PZC002",
  "linkedGunAngles": [],
  "linkedGunName": null,
  "linkedRotationSpeedCoeff": 1.0,
  "model": "content/gameplay/panasia/catapult/ZC002_Catapult/ZC002_Catapult.model",
  "name": "PZC002_Catapult",
  "rotateTime": 0.0,
  "typeinfo": {
   "nation": "Pan_Asia",
   "species": null,
   "type": "Catapult"
  }
 },
 {
  "angle": 0.0,
  "dist": 0.0,
  "hidePlane": false,
  "id": 4293063888,
  "index": "PZC001",
  "linkedGunAngles": [],
  "linkedGunName": null,
  "linkedRotationSpeedCoeff": 1.0,
  "model": "content/gameplay/panasia/catapult/ZC001_Catapult/ZC001_Catapult.model",
  "name": "PZC001_Catapult",
  "rotateTime": 0.0,
  "typeinfo": {
   "nation": "Pan_Asia",
   "species": null,
   "type": "Catapult"
  }
 }
]